<annotation>
	<folder />
	<filename>000047_jpg.rf.270b6d9dcc9ae3d201b2d21648050496.jpg</filename>
	<path>000047_jpg.rf.270b6d9dcc9ae3d201b2d21648050496.jpg</path>
	<source>
		<database>roboflow.com</database>
	</source>
	<size>
		<width>640</width>
		<height>640</height>
		<depth>3</depth>
	</size>
	<segmented>0</segmented>
	<object>
		<name>Metal</name>
		<pose>Unspecified</pose>
		<truncated>0</truncated>
		<difficult>0</difficult>
		<occluded>0</occluded>
		<bndbox>
			<xmin>10</xmin>
			<xmax>318</xmax>
			<ymin>72</ymin>
			<ymax>259</ymax>
		</bndbox>
		<polygon>
			<x1>94.98991</x1>
			<y1>74.464084</y1>
			<x2>91.049366</x2>
			<y2>72.789964</y2>
			<x3>81.972231</x3>
			<y3>71.123729</y3>
			<x4>72.995784</x4>
			<y4>71.377533</y4>
			<x5>64.120022</x5>
			<y5>73.551378</y5>
			<x6>55.361728</x6>
			<y6>77.965268</y6>
			<x7>45.081423</x7>
			<y7>86.008528</y7>
			<x8>37.32746</x8>
			<y8>93.24783</y8>
			<x9>28.185734</x9>
			<y9>106.676553</y9>
			<x10>20.065121</x10>
			<y10>123.250694</y10>
			<x11>15.616554</x11>
			<y11>136.37885</y11>
			<x12>12.757122</x12>
			<y12>147.157662</y12>
			<x13>9.765975</x13>
			<y13>171.751407</y13>
			<x14>9.265077</x14>
			<y14>178.526193</y14>
			<x15>9.392201</x15>
			<y15>189.113736</y15>
			<x16>11.686142</x16>
			<y16>200.204668</y16>
			<x17>16.875609</x17>
			<y17>217.531788</y17>
			<x18>21.66233</x18>
			<y18>227.178748</y18>
			<x19>28.975393</x19>
			<y19>236.02175</y19>
			<x20>37.894374</x20>
			<y20>242.835414</y20>
			<x21>50.552525</x21>
			<y21>247.48312</y21>
			<x22>60.842488</x22>
			<y22>247.787356</y22>
			<x23>68.89851</x23>
			<y23>246.308172</y23>
			<x24>72.345278</x24>
			<y24>246.729591</y24>
			<x25>127.718853</x25>
			<y25>249.604881</y25>
			<x26>195.088994</x26>
			<y26>252.67511</y26>
			<x27>244.012463</x27>
			<y27>255.000246</y27>
			<x28>271.469145</x28>
			<y28>256.131546</y28>
			<x29>274.062611</x29>
			<y29>256.607614</y29>
			<x30>277.082729</x30>
			<y30>257.056356</y30>
			<x31>283.976267</x31>
			<y31>257.899193</y31>
			<x32>293.362584</x32>
			<y32>257.298057</y32>
			<x33>307.307812</x33>
			<y33>253.8363</y33>
			<x34>314.393064</x34>
			<y34>250.171721</y34>
			<x35>315.196023</x35>
			<y35>249.157052</y35>
			<x36>315.25349</x36>
			<y36>242.089583</y36>
			<x37>314.817182</x37>
			<y37>233.769411</y37>
			<x38>313.618603</x38>
			<y38>219.076432</y38>
			<x39>313.172638</x39>
			<y39>202.408765</y39>
			<x40>312.961609</x40>
			<y40>190.221191</y40>
			<x41>313.378602</x41>
			<y41>181.846371</y41>
			<x42>313.963407</x42>
			<y42>176.671617</y42>
			<x43>316.688589</x43>
			<y43>163.332752</y43>
			<x44>316.336186</x44>
			<y44>156.612613</y44>
			<x45>315.164045</x45>
			<y45>150.587137</y45>
			<x46>313.665939</x46>
			<y46>146.509024</y46>
			<x47>313.021134</x47>
			<y47>142.376263</y47>
			<x48>313.404566</x48>
			<y48>133.36143</y48>
			<x49>313.905465</x49>
			<y49>126.586643</y49>
			<x50>302.644734</x50>
			<y50>124.09701</y50>
			<x51>223.309056</x51>
			<y51>105.096873</y51>
			<x52>149.210656</x52>
			<y52>88.008888</y52>
			<x53>111.5047</x53>
			<y53>79.185877</y53>
			<x54>101.097269</x54>
			<y54>76.641596</y54>
			<x55>94.98991</x55>
			<y55>74.464084</y55>
		</polygon>
	</object>
	<object>
		<name>Metal</name>
		<pose>Unspecified</pose>
		<truncated>0</truncated>
		<difficult>0</difficult>
		<occluded>0</occluded>
		<bndbox>
			<xmin>9</xmin>
			<xmax>360</xmax>
			<ymin>360</ymin>
			<ymax>560</ymax>
		</bndbox>
		<polygon>
			<x1>347.804967</x1>
			<y1>405.682819</y1>
			<x2>342.198506</x2>
			<y2>396.73052</y2>
			<x3>337.989465</x3>
			<y3>389.936295</y3>
			<x4>335.060378</x4>
			<y4>383.060097</y4>
			<x5>331.126958</x5>
			<y5>373.358486</y5>
			<x6>329.118295</x6>
			<y6>367.707665</y6>
			<x7>327.670532</x7>
			<y7>364.589572</y7>
			<x8>319.379575</x8>
			<y8>361.588662</y8>
			<x9>308.118844</x9>
			<y9>359.09903</y9>
			<x10>296.532147</x10>
			<y10>358.556761</y10>
			<x11>287.129049</x11>
			<y11>358.83789</y11>
			<x12>195.583718</x12>
			<y12>368.232698</y12>
			<x13>106.121298</x13>
			<y13>376.530865</y13>
			<x14>79.29264</x14>
			<y14>379.21232</y14>
			<x15>72.056358</x15>
			<y15>379.996839</y15>
			<x16>66.442773</x16>
			<y16>379.07203</y16>
			<x17>61.732833</x17>
			<y17>379.052591</y17>
			<x18>52.363297</x18>
			<y18>379.973734</y18>
			<x19>45.194138</x19>
			<y19>382.038281</y19>
			<x20>36.419064</x20>
			<y20>386.132164</y20>
			<x21>30.697668</x21>
			<y21>391.314804</y21>
			<x22>23.01083</x22>
			<y22>399.834132</y22>
			<x23>17.883896</x23>
			<y23>408.189513</y23>
			<x24>14.513908</x24>
			<y24>417.395616</y24>
			<x25>9.840064</x25>
			<y25>434.391175</y25>
			<x26>8.119212</x26>
			<y26>450.555451</y26>
			<x27>8.414148</x27>
			<y27>464.34306</y27>
			<x28>9.478479</x28>
			<y28>476.475985</y28>
			<x29>11.228301</x29>
			<y29>485.354196</y29>
			<x30>14.919661</x30>
			<y30>498.603203</y30>
			<x31>19.430761</x31>
			<y31>511.157548</y31>
			<x32>24.694477</x32>
			<y32>521.737204</y32>
			<x33>32.618783</x33>
			<y33>534.072953</y33>
			<x34>41.245361</x34>
			<y34>543.473995</y34>
			<x35>46.207018</x35>
			<y35>548.293533</y35>
			<x36>52.858495</x36>
			<y36>552.683766</y36>
			<x37>62.069878</x37>
			<y37>556.910053</y37>
			<x38>74.167131</x38>
			<y38>559.025031</y38>
			<x39>86.096572</x39>
			<y39>557.939942</y39>
			<x40>94.49534</x40>
			<y40>554.833402</y40>
			<x41>99.548025</x41>
			<y41>553.225484</y41>
			<x42>113.852779</x42>
			<y42>548.456377</y42>
			<x43>125.698315</x43>
			<y43>545.771256</y43>
			<x44>129.454267</x44>
			<y44>543.925303</y44>
			<x45>217.173989</x45>
			<y45>518.721436</y45>
			<x46>321.449186</x46>
			<y46>490.851886</y46>
			<x47>328.158132</x47>
			<y47>488.17465</y47>
			<x48>334.373302</x48>
			<y48>484.244712</y48>
			<x49>340.622035</x49>
			<y49>480.954788</y49>
			<x50>346.427335</x50>
			<y50>477.372181</y50>
			<x51>352.165512</x51>
			<y51>472.509547</y51>
			<x52>359.425699</x52>
			<y52>464.017544</y52>
			<x53>354.857132</x53>
			<y53>458.530669</y53>
			<x54>350.255003</x54>
			<y54>452.403782</y54>
			<x55>346.43905</x55>
			<y55>444.942219</y55>
			<x56>344.413607</x56>
			<y56>438.97139</y56>
			<x57>343.701678</x57>
			<y57>433.558603</y57>
			<x58>344.629228</x58>
			<y58>426.756492</y58>
			<x59>347.2466</x59>
			<y59>419.525075</y59>
			<x60>350.700493</x60>
			<y60>411.919005</y60>
			<x61>347.804967</x61>
			<y61>405.682819</y61>
		</polygon>
	</object>
	<object>
		<name>Plastic</name>
		<pose>Unspecified</pose>
		<truncated>0</truncated>
		<difficult>0</difficult>
		<occluded>0</occluded>
		<bndbox>
			<xmin>314</xmin>
			<xmax>565</xmax>
			<ymin>53</ymin>
			<ymax>575</ymax>
		</bndbox>
		<polygon>
			<x1>317.349701</x1>
			<y1>110.633077</y1>
			<x2>315.878033</x2>
			<y2>115.222466</y2>
			<x3>314.866577</x3>
			<y3>120.424544</y3>
			<x4>314.298553</x4>
			<y4>125.919305</y4>
			<x5>313.71375</x5>
			<y5>131.09406</y5>
			<x6>313.481347</x6>
			<y6>142.988951</y6>
			<x7>314.092589</x7>
			<y7>146.4817</y7>
			<x8>315.691382</x8>
			<y8>152.479852</y8>
			<x9>316.846743</x9>
			<y9>158.185322</y9>
			<x10>316.638246</x10>
			<y10>162.372731</y10>
			<x11>316.070223</x11>
			<y11>167.867493</y11>
			<x12>315.435075</x12>
			<y12>172.082228</y12>
			<x13>314.030531</x13>
			<y13>177.951643</y13>
			<x14>313.462507</x14>
			<y14>183.446405</y14>
			<x15>313.045514</x15>
			<y15>191.821224</y15>
			<x16>313.239762</x16>
			<y16>203.688792</y16>
			<x17>314.893964</x17>
			<y17>243.396934</y17>
			<x18>315.373491</x18>
			<y18>260.704614</y18>
			<x19>319.043479</x19>
			<y19>298.036087</y19>
			<x20>320.023905</x20>
			<y20>308.56898</y20>
			<x21>318.75361</x21>
			<y21>316.99845</y21>
			<x22>318.010651</x22>
			<y22>327.320633</y22>
			<x23>320.58987</x23>
			<y23>343.851678</y23>
			<x24>324.67432</x24>
			<y24>356.433347</y24>
			<x25>326.699763</x25>
			<y25>362.404175</y25>
			<x26>329.61207</x26>
			<y26>368.960367</y26>
			<x27>333.118839</x27>
			<y27>378.689301</y27>
			<x28>338.483241</x28>
			<y28>391.188997</y28>
			<x29>344.072919</x29>
			<y29>399.821289</y29>
			<x30>348.775736</x30>
			<y30>407.868217</y30>
			<x31>351.127143</x31>
			<y31>411.891681</y31>
			<x32>346.853512</x32>
			<y32>420.192413</y32>
			<x33>345.415405</x33>
			<y33>425.421816</y33>
			<x34>344.420732</x34>
			<y34>430.943901</y34>
			<x35>344.890602</x35>
			<y35>439.904086</y35>
			<x36>348.380589</x36>
			<y36>449.313013</y36>
			<x37>352.095854</x37>
			<y37>454.854537</y37>
			<x38>354.890694</x38>
			<y38>459.170683</y38>
			<x39>358.982267</x39>
			<y39>463.724862</y39>
			<x40>362.630409</x40>
			<y40>467.98636</y40>
			<x41>370.72965</x41>
			<y41>475.494686</y41>
			<x42>371.240207</x42>
			<y42>477.067394</y42>
			<x43>374.411354</x43>
			<y43>480.396196</y43>
			<x44>384.778097</x44>
			<y44>490.327954</y44>
			<x45>390.559492</x45>
			<y45>494.45283</y45>
			<x46>394.943468</x46>
			<y46>496.419633</y46>
			<x47>401.034047</x47>
			<y47>498.277137</y47>
			<x48>401.168296</x48>
			<y48>500.83719</y48>
			<x49>400.82555</x49>
			<y49>502.464547</y49>
			<x50>398.725858</x50>
			<y50>503.241183</y50>
			<x51>394.986687</x51>
			<y51>505.407142</y51>
			<x52>392.9709</x52>
			<y52>507.78381</y52>
			<x53>393.515019</x53>
			<y53>509.996531</y53>
			<x54>393.12193</x54>
			<y54>510.663868</y54>
			<x55>392.318972</x55>
			<y55>511.678536</y55>
			<x56>393.467209</x56>
			<y56>525.411496</y56>
			<x57>393.627895</x57>
			<y57>536.639051</y57>
			<x58>398.146119</x58>
			<y58>541.165905</y58>
			<x59>403.86039</x59>
			<y59>544.010756</y59>
			<x60>409.96775</x60>
			<y60>546.188267</y60>
			<x61>413.874731</x61>
			<y61>547.222376</y61>
			<x62>415.063655</x62>
			<y62>553.567857</y62>
			<x63>415.164341</x63>
			<y63>555.487898</y63>
			<x64>411.918945</x64>
			<y64>558.906558</y64>
			<x65>409.970283</x65>
			<y65>562.563252</y65>
			<x66>409.711442</x66>
			<y66>565.790643</y66>
			<x67>410.715774</x67>
			<y67>568.616052</y67>
			<x68>418.529737</x68>
			<y68>570.684267</y68>
			<x69>427.606871</x69>
			<y69>572.350502</y69>
			<x70>441.393945</x70>
			<y70>574.036175</y70>
			<x71>444.807152</x71>
			<y71>573.817581</y71>
			<x72>449.859838</x72>
			<y72>572.209663</y72>
			<x73>461.554344</x73>
			<y73>566.644481</y73>
			<x74>466.916213</x74>
			<y74>562.769192</y74>
			<x75>471.801087</x75>
			<y75>557.961207</y75>
			<x76>474.552708</x76>
			<y76>553.289844</y76>
			<x77>475.221417</x77>
			<y77>549.715124</y77>
			<x78>474.677299</x78>
			<y78>547.502402</y78>
			<x79>475.890128</x79>
			<y79>546.140403</y79>
			<x80>475.839784</x80>
			<y80>545.180383</y80>
			<x81>479.595737</x81>
			<y81>543.334431</y81>
			<x82>485.04151</x82>
			<y82>541.059175</y82>
			<x83>487.500729</x83>
			<y83>538.975188</y83>
			<x84>489.892823</x84>
			<y84>535.611177</y84>
			<x85>490.645438</x85>
			<y85>533.636488</y85>
			<x86>489.899947</x86>
			<y86>527.583688</y86>
			<x87>490.024538</x87>
			<y87>521.796244</y87>
			<x88>489.379734</x88>
			<y88>517.663484</y88>
			<x89>488.5839</x89>
			<y89>510.650664</y89>
			<x90>488.039781</x90>
			<y90>508.437942</y90>
			<x91>487.529225</x91>
			<y91>506.865233</y91>
			<x92>484.767947</x92>
			<y92>503.1891</y92>
			<x93>481.680706</x93>
			<y93>501.460331</y93>
			<x94>479.070457</x94>
			<y94>500.664257</y94>
			<x95>477.740162</x95>
			<y95>499.78621</y95>
			<x96>477.639475</x96>
			<y96>497.866172</y96>
			<x97>478.015783</x97>
			<y97>496.878827</y97>
			<x98>480.115475</x98>
			<y98>496.102192</y98>
			<x99>486.723734</x99>
			<y99>491.504917</y99>
			<x100>491.316206</x100>
			<y100>489.284309</y100>
			<x101>496.284986</x101>
			<y101>486.076357</y101>
			<x102>500.827116</x102>
			<y102>482.895731</y102>
			<x103>509.451161</x103>
			<y103>475.921787</y103>
			<x104>515.975514</x104>
			<y104>469.724478</y104>
			<x105>522.089998</x105>
			<y105>463.874501</y105>
			<x106>530.939322</x106>
			<y106>453.033155</y106>
			<x107>535.589262</x107>
			<y107>443.745078</y107>
			<x108>536.24119</x108>
			<y108>439.850351</y108>
			<x109>536.708527</x109>
			<y109>432.43555</y109>
			<x110>535.603509</x110>
			<y110>427.6901</y110>
			<x111>534.532055</x111>
			<y111>423.584663</y111>
			<x112>533.084291</x112>
			<y112>420.466571</y112>
			<x113>532.012836</x113>
			<y113>416.361133</y113>
			<x114>531.008505</x114>
			<y114>413.535722</y114>
			<x115>530.414043</x115>
			<y115>410.362982</y115>
			<x116>531.015629</x116>
			<y116>405.508233</y116>
			<x117>533.549095</x117>
			<y117>396.676785</y117>
			<x118>537.772385</x118>
			<y118>387.416033</y118>
			<x119>544.680169</x119>
			<y119>372.203891</y119>
			<x120>549.296547</x120>
			<y120>362.275801</y120>
			<x121>553.368806</x121>
			<y121>350.13499</y121>
			<x122>558.728142</x122>
			<y122>329.884715</y122>
			<x123>560.099124</x123>
			<y123>323.375287</y123>
			<x124>562.138816</x124>
			<y124>313.291137</y124>
			<x125>562.639715</x125>
			<y125>306.516349</y125>
			<x126>563.123834</x126>
			<y126>299.421556</y126>
			<x127>562.919927</x127>
			<y127>279.206492</y127>
			<x128>564.211595</x128>
			<y128>246.694556</y128>
			<x129>563.628849</x129>
			<y129>211.091851</y129>
			<x130>561.454435</x130>
			<y130>161.463505</y130>
			<x131>558.966245</x131>
			<y131>138.505004</y131>
			<x132>553.108068</x132>
			<y132>124.752607</y132>
			<x133>550.790222</x133>
			<y133>121.369156</y133>
			<x134>550.17898</x134>
			<y134>117.876407</y134>
			<x135>549.500613</x135>
			<y135>113.103632</y135>
			<x136>549.608424</x136>
			<y136>106.996184</y136>
			<x137>549.121773</x137>
			<y137>97.715993</y137>
			<x138>546.384401</x138>
			<y138>86.332377</y138>
			<x139>542.065016</x139>
			<y139>69.270615</y139>
			<x140>538.759621</x140>
			<y140>63.381761</y140>
			<x141>534.29174</x141>
			<y141>59.814926</y141>
			<x142>528.560688</x142>
			<y142>56.65007</y142>
			<x143>517.726607</x143>
			<y143>54.133113</y143>
			<x144>506.056005</x144>
			<y144>51.990811</y144>
			<x145>488.496198</x145>
			<y145>51.831083</y145>
			<x146>471.003515</x146>
			<y146>52.951382</y146>
			<x147>451.921696</x147>
			<y147>56.421024</y147>
			<x148>427.377323</x148>
			<y148>61.845915</y148>
			<x149>412.612356</x149>
			<y149>66.002334</y149>
			<x150>389.431839</x150>
			<y150>72.945285</y150>
			<x151>362.528933</x151>
			<y151>82.374202</y151>
			<x152>334.530667</x152>
			<y152>95.405163</y152>
			<x153>320.937842</x153>
			<y153>105.587059</y153>
			<x154>317.349701</x154>
			<y154>110.633077</y154>
		</polygon>
	</object>
	<object>
		<name>Plastic</name>
		<pose>Unspecified</pose>
		<truncated>0</truncated>
		<difficult>0</difficult>
		<occluded>0</occluded>
		<bndbox>
			<xmin>394</xmin>
			<xmax>492</xmax>
			<ymin>511</ymin>
			<ymax>575</ymax>
		</bndbox>
		<polygon>
			<x1>460.717823</x1>
			<y1>567.019137</y1>
			<x2>464.030343</x2>
			<y2>564.880502</y2>
			<x3>467.735952</x3>
			<y3>562.07453</y3>
			<x4>470.588259</x4>
			<y4>559.323207</y4>
			<x5>472.980353</x5>
			<y5>555.959195</y5>
			<x6>473.732968</x6>
			<y6>553.984507</y6>
			<x7>474.485584</x7>
			<y7>552.009818</y7>
			<x8>474.384898</x8>
			<y8>550.089779</y8>
			<x9>474.250649</x9>
			<y9>547.529726</y9>
			<x10>475.053607</x10>
			<y10>546.515058</y10>
			<x11>475.413134</x11>
			<y11>545.207707</y11>
			<x12>475.823003</x12>
			<y12>544.860376</y12>
			<x13>480.005606</x13>
			<y13>542.9871</y13>
			<x14>484.20499</x14>
			<y14>541.43383</y14>
			<x15>485.861249</x15>
			<y15>540.364514</y15>
			<x16>487.893817</x16>
			<y16>538.307851</y16>
			<x17>489.892823</x17>
			<y17>535.611177</y17>
			<x18>490.645438</x18>
			<y18>533.636488</y18>
			<x19>489.933509</x19>
			<y19>528.223701</y19>
			<x20>489.990976</x20>
			<y20>521.156232</y20>
			<x21>489.362953</x21>
			<y21>517.343477</y21>
			<x22>488.701367</x22>
			<y22>512.89071</y22>
			<x23>488.5839</x23>
			<y23>510.650664</y23>
			<x24>488.106905</x24>
			<y24>509.717968</y24>
			<x25>487.287166</x25>
			<y25>510.412629</y25>
			<x26>485.69803</x26>
			<y26>512.761973</y26>
			<x27>480.302599</x27>
			<y27>515.997249</y27>
			<x28>476.513085</x28>
			<y28>517.203188</y28>
			<x29>470.180448</x29>
			<y29>518.89308</y29>
			<x30>460.844473</x30>
			<y30>520.454235</y30>
			<x31>449.751553</x31>
			<y31>521.164669</y31>
			<x32>439.938584</x32>
			<y32>521.793129</y32>
			<x33>426.645285</x33>
			<y33>521.360157</y33>
			<x34>419.341878</x34>
			<y34>520.864651</y34>
			<x35>414.615157</x35>
			<y35>520.525206</y35>
			<x36>411.59504</x36>
			<y36>520.076463</y36>
			<x37>402.501124</x37>
			<y37>518.090221</y37>
			<x38>400.317526</x38>
			<y38>517.266824</y38>
			<x39>398.13393</x39>
			<y39>516.443426</y39>
			<x40>395.456557</x40>
			<y40>514.367326</y40>
			<x41>394.092699</x41>
			<y41>512.849265</y41>
			<x42>392.728842</x42>
			<y42>511.331206</y42>
			<x43>392.86309</x43>
			<y43>513.891259</y43>
			<x44>394.054546</x44>
			<y44>536.611726</y44>
			<x45>396.33883</x45>
			<y45>539.355164</y45>
			<x46>400.78993</x46>
			<y46>542.601993</y46>
			<x47>408.671016</x47>
			<y47>545.950234</y47>
			<x48>413.874731</x48>
			<y48>547.222376</y48>
			<x49>415.181122</x49>
			<y49>555.807903</y49>
			<x50>411.935726</x50>
			<y50>559.226565</y50>
			<x51>410.003845</x51>
			<y51>563.203265</y51>
			<x52>409.745005</x52>
			<y52>566.430655</y52>
			<x53>410.715774</x53>
			<y53>568.616052</y53>
			<x54>414.196105</x54>
			<y54>569.677484</y54>
			<x55>419.399819</x55>
			<y55>570.949625</y55>
			<x56>425.013404</x56>
			<y56>571.874435</y56>
			<x57>430.200338</x57>
			<y57>572.826569</y57>
			<x58>437.520527</x58>
			<y58>573.642082</y58>
			<x59>441.393945</x59>
			<y59>574.036175</y59>
			<x60>443.95385</x60>
			<y60>573.872229</y60>
			<x61>446.906843</x61>
			<y61>573.040946</y61>
			<x62>452.369399</x62>
			<y62>571.085696</y62>
			<x63>456.142132</x63>
			<y63>569.559751</y63>
			<x64>460.717823</x64>
			<y64>567.019137</y64>
		</polygon>
	</object>
	<object>
		<name>Metal</name>
		<pose>Unspecified</pose>
		<truncated>0</truncated>
		<difficult>0</difficult>
		<occluded>0</occluded>
		<bndbox>
			<xmin>63</xmin>
			<xmax>107</xmax>
			<ymin>403</ymin>
			<ymax>476</ymax>
		</bndbox>
		<polygon>
			<x1>75.558535</x1>
			<y1>414.128247</y1>
			<x2>64.417804</x2>
			<y2>430.253646</y2>
			<x3>62.227083</x3>
			<y3>437.457736</y3>
			<x4>61.568031</x4>
			<y4>449.379954</y4>
			<x5>65.66926</x5>
			<y5>462.281629</y5>
			<x6>72.112242</x6>
			<y6>470.859272</y6>
			<x7>79.566678</x7>
			<y7>474.234837</y7>
			<x8>86.870085</x8>
			<y8>474.730343</y8>
			<x9>92.33264</x9>
			<y9>472.775093</y9>
			<x10>96.004686</x10>
			<y10>469.329108</y10>
			<x11>99.031929</x11>
			<y11>461.750363</y11>
			<x12>101.5893</x12>
			<y12>445.211431</y12>
			<x13>104.84182</x13>
			<y13>433.765281</y13>
			<x14>106.488423</x14>
			<y14>424.348469</y14>
			<x15>105.081346</x15>
			<y15>413.8429</y15>
			<x16>101.742388</x16>
			<y16>407.314032</y16>
			<x17>94.597135</x17>
			<y17>401.671096</y17>
			<x18>91.167147</x18>
			<y18>401.569684</y18>
			<x19>83.195031</x19>
			<y19>404.6489</y19>
			<x20>75.558535</x20>
			<y20>414.128247</y20>
		</polygon>
	</object>
	<object>
		<name>Metal</name>
		<pose>Unspecified</pose>
		<truncated>0</truncated>
		<difficult>0</difficult>
		<occluded>0</occluded>
		<bndbox>
			<xmin>61</xmin>
			<xmax>106</xmax>
			<ymin>85</ymin>
			<ymax>164</ymax>
		</bndbox>
		<polygon>
			<x1>98.66243</x1>
			<y1>128.170542</y1>
			<x2>100.292253</x2>
			<y2>118.433723</y2>
			<x3>101.253365</x3>
			<y3>112.271623</y3>
			<x4>103.887518</x4>
			<y4>105.360215</y4>
			<x5>105.174594</x5>
			<y5>97.250753</y5>
			<x6>103.13237</x6>
			<y6>90.959918</y6>
			<x7>99.961223</x7>
			<y7>87.631116</y7>
			<x8>97.69372</x8>
			<y8>85.207686</y8>
			<x9>93.326525</x9>
			<y9>83.56089</y9>
			<x10>89.52023</x10>
			<y10>84.446822</y10>
			<x11>84.96132</x11>
			<y11>87.307443</y11>
			<x12>82.142576</x12>
			<y12>90.698779</y12>
			<x13>77.049204</x13>
			<y13>99.694173</y13>
			<x14>66.419028</x14>
			<y14>117.392281</y14>
			<x15>62.588828</x15>
			<y15>125.985695</y15>
			<x16>60.807976</x16>
			<y16>132.842455</y16>
			<x17>59.880426</x17>
			<y17>139.644567</y17>
			<x18>60.266391</x18>
			<y18>147.004718</y18>
			<x19>61.798059</x19>
			<y19>151.722844</y19>
			<x20>64.626461</x20>
			<y20>156.679003</y20>
			<x21>68.701254</x21>
			<y21>160.913177</y21>
			<x22>74.398744</x22>
			<y22>163.438019</y22>
			<x23>82.09524</x23>
			<y23>163.266187</y23>
			<x24>85.390978</x24>
			<y24>160.807547</y24>
			<x25>90.175166</x25>
			<y25>154.079522</y25>
			<x26>93.64584</x26>
			<y26>146.793458</y26>
			<x27>96.656301</x27>
			<y27>138.894705</y27>
			<x28>98.66243</x28>
			<y28>128.170542</y28>
		</polygon>
	</object>
</annotation>