<annotation>
	<folder />
	<filename>000054_jpg.rf.a4056c9008f34b47231af2d657d94958.jpg</filename>
	<path>000054_jpg.rf.a4056c9008f34b47231af2d657d94958.jpg</path>
	<source>
		<database>roboflow.com</database>
	</source>
	<size>
		<width>640</width>
		<height>640</height>
		<depth>3</depth>
	</size>
	<segmented>0</segmented>
	<object>
		<name>Cardboard</name>
		<pose>Unspecified</pose>
		<truncated>0</truncated>
		<difficult>0</difficult>
		<occluded>0</occluded>
		<bndbox>
			<xmin>201</xmin>
			<xmax>512</xmax>
			<ymin>131</ymin>
			<ymax>369</ymax>
		</bndbox>
		<polygon>
			<x1>293.228335</x1>
			<y1>156.383398</y1>
			<x2>200.468729</x2>
			<y2>242.739285</y2>
			<x3>200.92839</x3>
			<y3>249.915111</y3>
			<x4>216.949098</x4>
			<y4>268.710516</y4>
			<x5>328.299796</x5>
			<y5>329.238016</y5>
			<x6>397.549115</x6>
			<y6>367.7924</y6>
			<x7>455.914871</x7>
			<y7>317.8878</y7>
			<x8>508.841108</x8>
			<y8>261.254114</y8>
			<x9>510.576593</x9>
			<y9>249.253031</y9>
			<x10>355.986977</x10>
			<y10>168.54106</y10>
			<x11>307.824287</x11>
			<y11>143.163236</y11>
			<x12>284.638568</x12>
			<y12>129.795827</y12>
			<x13>290.82141</x13>
			<y13>154.644701</y13>
			<x14>293.228335</x14>
			<y14>156.383398</y14>
		</polygon>
	</object>
	<object>
		<name>Metal</name>
		<pose>Unspecified</pose>
		<truncated>0</truncated>
		<difficult>0</difficult>
		<occluded>0</occluded>
		<bndbox>
			<xmin>256</xmin>
			<xmax>289</xmax>
			<ymin>138</ymin>
			<ymax>178</ymax>
		</bndbox>
		<polygon>
			<x1>256.068143</x1>
			<y1>169.195947</y1>
			<x2>264.468369</x2>
			<y2>176.535413</y2>
			<x3>270.755643</x3>
			<y3>176.951964</y3>
			<x4>287.300795</x4>
			<y4>161.58271</y4>
			<x5>287.856832</x5>
			<y5>147.45825</y5>
			<x6>280.960006</x6>
			<y6>137.525931</y6>
			<x7>263.207681</x7>
			<y7>137.307679</y7>
			<x8>254.56893</x8>
			<y8>162.080693</y8>
			<x9>256.068143</x9>
			<y9>169.195947</y9>
		</polygon>
	</object>
	<object>
		<name>Metal</name>
		<pose>Unspecified</pose>
		<truncated>0</truncated>
		<difficult>0</difficult>
		<occluded>0</occluded>
		<bndbox>
			<xmin>188</xmin>
			<xmax>257</xmax>
			<ymin>150</ymin>
			<ymax>180</ymax>
		</bndbox>
		<polygon>
			<x1>188.231335</x1>
			<y1>175.497274</y1>
			<x2>198.292909</x2>
			<y2>179.451791</y2>
			<x3>232.598123</x3>
			<y3>177.452928</y3>
			<x4>249.240947</x4>
			<y4>176.639778</y4>
			<x5>254.78458</x5>
			<y5>175.220717</y5>
			<x6>256.118106</x6>
			<y6>169.975928</y6>
			<x7>254.598908</x7>
			<y7>162.548682</y7>
			<x8>254.870962</x8>
			<y8>153.764437</y8>
			<x9>195.720615</x9>
			<y9>149.068874</y9>
			<x10>187.833882</x10>
			<y10>156.261284</y10>
			<x11>187.275911</x11>
			<y11>167.097708</y11>
			<x12>188.231335</x12>
			<y12>175.497274</y12>
		</polygon>
	</object>
	<object>
		<name>Metal</name>
		<pose>Unspecified</pose>
		<truncated>0</truncated>
		<difficult>0</difficult>
		<occluded>0</occluded>
		<bndbox>
			<xmin>195</xmin>
			<xmax>263</xmax>
			<ymin>177</ymin>
			<ymax>209</ymax>
		</bndbox>
		<polygon>
			<x1>222.400521</x1>
			<y1>177.890534</y1>
			<x2>204.768109</x2>
			<y2>179.544236</y2>
			<x3>194.424488</x3>
			<y3>184.217969</y3>
			<x4>194.650129</x4>
			<y4>197.513989</y4>
			<x5>198.368343</x5>
			<y5>206.692047</y5>
			<x6>203.656037</x6>
			<y6>207.793154</y6>
			<x7>237.071907</x7>
			<y7>191.910627</y7>
			<x8>247.881312</x8>
			<y8>187.992649</y8>
			<x9>256.12778</x9>
			<y9>186.416102</y9>
			<x10>261.859337</x10>
			<y10>184.672935</y10>
			<x11>261.953459</x11>
			<y11>176.368793</y11>
			<x12>259.092677</x12>
			<y12>177.318374</y12>
			<x13>249.934627</x13>
			<y13>177.695408</y13>
			<x14>222.400521</x14>
			<y14>177.890534</y14>
		</polygon>
	</object>
	<object>
		<name>Metal</name>
		<pose>Unspecified</pose>
		<truncated>0</truncated>
		<difficult>0</difficult>
		<occluded>0</occluded>
		<bndbox>
			<xmin>200</xmin>
			<xmax>257</xmax>
			<ymin>188</ymin>
			<ymax>232</ymax>
		</bndbox>
		<polygon>
			<x1>255.587859</x1>
			<y1>194.276484</y1>
			<x2>253.059087</x2>
			<y2>187.377798</y2>
			<x3>247.455499</x3>
			<y3>187.860881</y3>
			<x4>235.67649</x4>
			<y4>192.931406</y4>
			<x5>201.47894</x5>
			<y5>209.64237</y5>
			<x6>199.055899</x6>
			<y6>214.167751</y6>
			<x7>201.754546</x7>
			<y7>223.718372</y7>
			<x8>207.649855</x8>
			<y8>231.047214</y8>
			<x9>214.460935</x9>
			<y9>229.86746</y9>
			<x10>255.587859</x10>
			<y10>194.276484</y10>
		</polygon>
	</object>
	<object>
		<name>Metal</name>
		<pose>Unspecified</pose>
		<truncated>0</truncated>
		<difficult>0</difficult>
		<occluded>0</occluded>
		<bndbox>
			<xmin>148</xmin>
			<xmax>189</xmax>
			<ymin>135</ymin>
			<ymax>189</ymax>
		</bndbox>
		<polygon>
			<x1>147.427701</x1>
			<y1>137.947277</y1>
			<x2>147.956673</x2>
			<y2>178.783431</y2>
			<x3>152.704447</x3>
			<y3>187.744922</y3>
			<x4>182.525566</x4>
			<y4>187.416538</y4>
			<x5>187.957345</x5>
			<y5>180.993485</y5>
			<x6>186.724701</x6>
			<y6>138.945705</y6>
			<x7>181.593019</x7>
			<y7>133.764467</y7>
			<x8>155.316369</x8>
			<y8>134.042902</y8>
			<x9>147.427701</x9>
			<y9>137.947277</y9>
		</polygon>
	</object>
	<object>
		<name>Metal</name>
		<pose>Unspecified</pose>
		<truncated>0</truncated>
		<difficult>0</difficult>
		<occluded>0</occluded>
		<bndbox>
			<xmin>87</xmin>
			<xmax>148</xmax>
			<ymin>133</ymin>
			<ymax>166</ymax>
		</bndbox>
		<polygon>
			<x1>90.754229</x1>
			<y1>136.082385</y1>
			<x2>87.361584</x2>
			<y2>141.76031</y2>
			<x3>86.39585</x3>
			<y3>149.488925</y3>
			<x4>87.865084</x4>
			<y4>156.13619</y4>
			<x5>98.184533</x5>
			<y5>160.858574</y5>
			<x6>146.443599</x6>
			<y6>164.936112</y6>
			<x7>147.30779</x7>
			<y7>136.075323</y7>
			<x8>100.51409</x8>
			<y8>132.06898</y8>
			<x9>90.754229</x9>
			<y9>136.082385</y9>
		</polygon>
	</object>
	<object>
		<name>Metal</name>
		<pose>Unspecified</pose>
		<truncated>0</truncated>
		<difficult>0</difficult>
		<occluded>0</occluded>
		<bndbox>
			<xmin>73</xmin>
			<xmax>149</xmax>
			<ymin>171</ymin>
			<ymax>210</ymax>
		</bndbox>
		<polygon>
			<x1>85.387892</x1>
			<y1>169.589697</y1>
			<x2>76.787494</x2>
			<y2>175.414484</y2>
			<x3>72.38721</x3>
			<y3>184.909004</y3>
			<x4>74.076282</x4>
			<y4>194.988186</y4>
			<x5>125.905607</x5>
			<y5>209.191874</y5>
			<x6>137.320693</x6>
			<y6>208.213593</y6>
			<x7>140.873221</x7>
			<y7>205.031607</y7>
			<x8>145.553298</x8>
			<y8>199.904981</y8>
			<x9>147.736517</x9>
			<y9>191.635692</y9>
			<x10>145.723493</x10>
			<y10>186.27274</y10>
			<x11>141.047603</x11>
			<y11>181.691257</y11>
			<x12>91.021458</x12>
			<y12>169.574603</y12>
			<x13>85.387892</x13>
			<y13>169.589697</y13>
		</polygon>
	</object>
	<object>
		<name>Metal</name>
		<pose>Unspecified</pose>
		<truncated>0</truncated>
		<difficult>0</difficult>
		<occluded>0</occluded>
		<bndbox>
			<xmin>68</xmin>
			<xmax>140</xmax>
			<ymin>216</ymin>
			<ymax>266</ymax>
		</bndbox>
		<polygon>
			<x1>137.142123</x1>
			<y1>241.262052</y1>
			<x2>95.692522</x2>
			<y2>216.432547</y2>
			<x3>86.018724</x3>
			<y3>215.273848</y3>
			<x4>78.475929</x4>
			<y4>218.062021</y4>
			<x5>71.49691</x5>
			<y5>219.877874</y5>
			<x6>66.848744</x6>
			<y6>228.760523</y6>
			<x7>66.882592</x7>
			<y7>235.804582</y7>
			<x8>107.976329</x8>
			<y8>261.594292</y8>
			<x9>113.809748</x9>
			<y9>264.699122</y9>
			<x10>123.541565</x10>
			<y10>263.505763</y10>
			<x11>131.390262</x11>
			<y11>258.977403</y11>
			<x12>136.842026</x12>
			<y12>252.866342</y12>
			<x13>138.779298</x13>
			<y13>247.273217</y13>
			<x14>137.142123</x14>
			<y14>241.262052</y14>
		</polygon>
	</object>
	<object>
		<name>Metal</name>
		<pose>Unspecified</pose>
		<truncated>0</truncated>
		<difficult>0</difficult>
		<occluded>0</occluded>
		<bndbox>
			<xmin>136</xmin>
			<xmax>193</xmax>
			<ymin>189</ymin>
			<ymax>243</ymax>
		</bndbox>
		<polygon>
			<x1>177.971523</x1>
			<y1>187.995046</y1>
			<x2>158.022118</x2>
			<y2>189.314017</y2>
			<x3>134.845435</x3>
			<y3>224.955135</y3>
			<x4>137.314252</x4>
			<y4>230.917844</y4>
			<x5>143.753351</x5>
			<y5>236.962373</y5>
			<x6>156.607694</x6>
			<y6>242.16337</y6>
			<x7>170.445822</x7>
			<y7>236.659709</y7>
			<x8>192.235146</x8>
			<y8>198.90733</y8>
			<x9>188.073069</x9>
			<y9>192.573548</y9>
			<x10>177.971523</x10>
			<y10>187.995046</y10>
		</polygon>
	</object>
	<object>
		<name>Metal</name>
		<pose>Unspecified</pose>
		<truncated>0</truncated>
		<difficult>0</difficult>
		<occluded>0</occluded>
		<bndbox>
			<xmin>160</xmin>
			<xmax>215</xmax>
			<ymin>218</ymin>
			<ymax>273</ymax>
		</bndbox>
		<polygon>
			<x1>204.138914</x1>
			<y1>254.425397</y1>
			<x2>200.472599</x2>
			<y2>249.315355</y2>
			<x3>200.042916</x3>
			<y3>242.607518</y3>
			<x4>214.223047</x4>
			<y4>229.411585</y4>
			<x5>207.649855</x5>
			<y5>231.047214</y5>
			<x6>201.378696</x6>
			<y6>224.366585</y6>
			<x7>199.49364</x7>
			<y7>217.743549</y7>
			<x8>194.423849</x8>
			<y8>216.786323</y8>
			<x9>185.671627</x9>
			<y9>216.983133</y9>
			<x10>178.51661</x10>
			<y10>222.567123</y10>
			<x11>158.874405</x11>
			<y11>258.002297</y11>
			<x12>160.501587</x12>
			<y12>263.857467</y12>
			<x13>170.009378</x13>
			<y13>268.9403</y13>
			<x14>181.080527</x14>
			<y14>272.366257</y14>
			<x15>192.0698</x15>
			<y15>271.256209</y15>
			<x16>197.285611</x16>
			<y16>267.977308</y16>
			<x17>204.138914</x17>
			<y17>254.425397</y17>
		</polygon>
	</object>
	<object>
		<name>Metal</name>
		<pose>Unspecified</pose>
		<truncated>0</truncated>
		<difficult>0</difficult>
		<occluded>0</occluded>
		<bndbox>
			<xmin>218</xmin>
			<xmax>294</xmax>
			<ymin>291</ymin>
			<ymax>342</ymax>
		</bndbox>
		<polygon>
			<x1>293.425002</x1>
			<y1>322.345096</y1>
			<x2>289.69873</x2>
			<y2>316.299077</y2>
			<x3>276.170691</x3>
			<y3>310.354442</y3>
			<x4>247.941291</x4>
			<y4>289.921725</y4>
			<x5>240.842359</x5>
			<y5>289.865623</y5>
			<x6>230.190902</x6>
			<y6>292.991508</y6>
			<x7>221.502505</x7>
			<y7>300.700364</y7>
			<x8>217.360094</x8>
			<y8>310.96275</y8>
			<x9>236.661594</x9>
			<y9>319.076237</y9>
			<x10>259.96916</x10>
			<y10>337.603637</y10>
			<x11>264.613137</x11>
			<y11>338.429096</y11>
			<x12>271.258211</x12>
			<y12>341.173476</y12>
			<x13>280.592259</x13>
			<y13>337.028304</y13>
			<x14>290.082319</x14>
			<y14>328.803002</y14>
			<x15>293.425002</x15>
			<y15>322.345096</y15>
		</polygon>
	</object>
	<object>
		<name>Metal</name>
		<pose>Unspecified</pose>
		<truncated>0</truncated>
		<difficult>0</difficult>
		<occluded>0</occluded>
		<bndbox>
			<xmin>103</xmin>
			<xmax>183</xmax>
			<ymin>322</ymin>
			<ymax>364</ymax>
		</bndbox>
		<polygon>
			<x1>181.974719</x1>
			<y1>344.966556</y1>
			<x2>173.852671</x2>
			<y2>322.422771</y2>
			<x3>162.089777</x3>
			<y3>321.229219</y3>
			<x4>105.553947</x4>
			<y4>334.544416</y4>
			<x5>101.823488</x5>
			<y5>338.206505</y5>
			<x6>104.702002</x6>
			<y6>350.565059</y6>
			<x7>110.37135</x7>
			<y7>360.882057</y7>
			<x8>116.590611</x8>
			<y8>363.494669</y8>
			<x9>173.978068</x9>
			<y9>350.443007</y9>
			<x10>181.974719</x10>
			<y10>344.966556</y10>
		</polygon>
	</object>
	<object>
		<name>Metal</name>
		<pose>Unspecified</pose>
		<truncated>0</truncated>
		<difficult>0</difficult>
		<occluded>0</occluded>
		<bndbox>
			<xmin>349</xmin>
			<xmax>431</xmax>
			<ymin>362</ymin>
			<ymax>409</ymax>
		</bndbox>
		<polygon>
			<x1>354.115191</x1>
			<y1>403.204642</y1>
			<x2>361.919729</x2>
			<y2>407.760405</y2>
			<x3>370.919833</x3>
			<y3>408.175466</y3>
			<x4>375.156047</x4>
			<y4>405.893115</y4>
			<x5>377.093319</x5>
			<y5>400.29999</y5>
			<x6>399.565692</x6>
			<y6>396.0156</y6>
			<x7>415.770774</x7>
			<y7>391.626651</y7>
			<x8>425.084836</x8>
			<y8>387.169487</y8>
			<x9>429.61696</x9>
			<y9>382.990953</y9>
			<x10>427.967858</x10>
			<y10>373.535756</y10>
			<x11>421.140981</x11>
			<y11>364.695409</y11>
			<x12>416.089241</x12>
			<y12>360.762141</y12>
			<x13>408.228617</x13>
			<y13>361.846471</y13>
			<x14>398.806571</x14>
			<y14>367.875711</y14>
			<x15>383.237146</x15>
			<y15>375.672347</y15>
			<x16>359.397398</x16>
			<y16>378.157468</y16>
			<x17>351.450711</x17>
			<y17>384.413901</y17>
			<x18>348.106093</x18>
			<y18>387.583772</y18>
			<x19>349.605307</x19>
			<y19>394.699027</y19>
			<x20>354.115191</x20>
			<y20>403.204642</y20>
		</polygon>
	</object>
	<object>
		<name>Metal</name>
		<pose>Unspecified</pose>
		<truncated>0</truncated>
		<difficult>0</difficult>
		<occluded>0</occluded>
		<bndbox>
			<xmin>393</xmin>
			<xmax>466</xmax>
			<ymin>391</ymin>
			<ymax>454</ymax>
		</bndbox>
		<polygon>
			<x1>432.310463</x1>
			<y1>451.102215</y1>
			<x2>435.756941</x2>
			<y2>452.78034</y2>
			<x3>445.744697</x3>
			<y3>449.066814</y3>
			<x4>453.051539</x4>
			<y4>449.110801</y4>
			<x5>456.080261</x5>
			<y5>447.52512</y5>
			<x6>455.860423</x6>
			<y6>444.093204</y6>
			<x7>462.22377</x7>
			<y7>439.181656</y7>
			<x8>465.368534</x8>
			<y8>432.89186</y8>
			<x9>440.240056</x9>
			<y9>398.969292</y9>
			<x10>420.67069</x10>
			<y10>389.931943</y10>
			<x11>414.979104</x11>
			<y11>392.299094</y11>
			<x12>403.76387</x12>
			<y12>396.397299</y12>
			<x13>395.095459</x13>
			<y13>404.418147</y13>
			<x14>392.022578</x14>
			<y14>415.087951</y14>
			<x15>404.396956</x15>
			<y15>429.085307</y15>
			<x16>417.193279</x16>
			<y16>436.638361</y16>
			<x17>424.615843</x17>
			<y17>448.26241</y17>
			<x18>432.310463</x18>
			<y18>451.102215</y18>
		</polygon>
	</object>
	<object>
		<name>Metal</name>
		<pose>Unspecified</pose>
		<truncated>0</truncated>
		<difficult>0</difficult>
		<occluded>0</occluded>
		<bndbox>
			<xmin>308</xmin>
			<xmax>399</xmax>
			<ymin>546</ymin>
			<ymax>588</ymax>
		</bndbox>
		<polygon>
			<x1>385.616712</x1>
			<y1>549.648934</y1>
			<x2>324.565193</x2>
			<y2>544.594411</y2>
			<x3>315.764942</x3>
			<y3>547.299274</y3>
			<x4>309.255577</x4>
			<y4>556.446949</y4>
			<x5>307.27221</x5>
			<y5>567.836162</y5>
			<x6>308.325625</x6>
			<y6>574.507656</y6>
			<x7>316.072141</x7>
			<y7>581.415477</y7>
			<x8>376.925742</x8>
			<y8>586.63811</y8>
			<x9>383.93474</x9>
			<y9>585.290245</y9>
			<x10>390.815768</x10>
			<y10>585.202465</y10>
			<x11>396.187592</x11>
			<y11>577.843434</y11>
			<x12>397.983033</x12>
			<y12>566.778328</y12>
			<x13>397.203608</x13>
			<y13>554.610623</y13>
			<x14>385.616712</x14>
			<y14>549.648934</y14>
		</polygon>
	</object>
	<object>
		<name>Metal</name>
		<pose>Unspecified</pose>
		<truncated>0</truncated>
		<difficult>0</difficult>
		<occluded>0</occluded>
		<bndbox>
			<xmin>443</xmin>
			<xmax>457</xmax>
			<ymin>441</ymin>
			<ymax>450</ymax>
		</bndbox>
		<polygon>
			<x1>444.967207</x1>
			<y1>440.187144</y1>
			<x2>441.780537</x2>
			<y2>442.56492</y2>
			<x3>446.100563</x3>
			<y3>448.106608</y3>
			<x4>451.81407</x4>
			<y4>449.339483</y4>
			<x5>456.228216</x5>
			<y5>446.577028</y5>
			<x6>451.234497</x6>
			<y6>440.291704</y6>
			<x7>444.967207</x7>
			<y7>440.187144</y7>
		</polygon>
	</object>
	<object>
		<name>Metal</name>
		<pose>Unspecified</pose>
		<truncated>0</truncated>
		<difficult>0</difficult>
		<occluded>0</occluded>
		<bndbox>
			<xmin>280</xmin>
			<xmax>285</xmax>
			<ymin>327</ymin>
			<ymax>333</ymax>
		</bndbox>
		<polygon>
			<x1>280.438499</x1>
			<y1>328.112291</y1>
			<x2>278.549256</x2>
			<y2>331.197363</y2>
			<x3>280.50039</x3>
			<y3>332.336303</y3>
			<x4>284.180887</x4>
			<y4>327.894234</y4>
			<x5>284.238908</x5>
			<y5>325.542176</y5>
			<x6>280.438499</x6>
			<y6>328.112291</y6>
		</polygon>
	</object>
	<object>
		<name>Metal</name>
		<pose>Unspecified</pose>
		<truncated>0</truncated>
		<difficult>0</difficult>
		<occluded>0</occluded>
		<bndbox>
			<xmin>139</xmin>
			<xmax>147</xmax>
			<ymin>195</ymin>
			<ymax>202</ymax>
		</bndbox>
		<polygon>
			<x1>137.700732</x1>
			<y1>197.857272</y1>
			<x2>140.177606</x2>
			<y2>200.687943</y2>
			<x3>145.819231</x3>
			<y3>197.540809</y3>
			<x4>140.76749</x4>
			<y4>193.607542</y4>
			<x5>137.700732</x5>
			<y5>197.857272</y5>
		</polygon>
	</object>
	<object>
		<name>Metal</name>
		<pose>Unspecified</pose>
		<truncated>0</truncated>
		<difficult>0</difficult>
		<occluded>0</occluded>
		<bndbox>
			<xmin>348</xmin>
			<xmax>354</xmax>
			<ymin>397</ymin>
			<ymax>404</ymax>
		</bndbox>
		<polygon>
			<x1>349.481207</x1>
			<y1>402.53518</y1>
			<x2>352.539908</x2>
			<y2>401.417487</y2>
			<x3>348.437785</x3>
			<y3>396.019682</y3>
			<x4>346.984348</x4>
			<y4>399.392517</y4>
			<x5>349.481207</x5>
			<y5>402.53518</y5>
		</polygon>
	</object>
</annotation>