<annotation>
	<folder />
	<filename>000064_jpg.rf.0b13f285b4f7d5027366cfdc96ea5c66.jpg</filename>
	<path>000064_jpg.rf.0b13f285b4f7d5027366cfdc96ea5c66.jpg</path>
	<source>
		<database>roboflow.com</database>
	</source>
	<size>
		<width>640</width>
		<height>640</height>
		<depth>3</depth>
	</size>
	<segmented>0</segmented>
	<object>
		<name>Plastic</name>
		<pose>Unspecified</pose>
		<truncated>0</truncated>
		<difficult>0</difficult>
		<occluded>0</occluded>
		<bndbox>
			<xmin>213</xmin>
			<xmax>472</xmax>
			<ymin>118</ymin>
			<ymax>480</ymax>
		</bndbox>
		<polygon>
			<x1>330.050943</x1>
			<y1>274.920377</y1>
			<x2>329.883398</x2>
			<y2>269.1519</y2>
			<x3>323.00782</x3>
			<y3>264.373423</y3>
			<x4>349.087809</x4>
			<y4>252.261987</y4>
			<x5>337.986917</x5>
			<y5>240.794369</y5>
			<x6>350.957403</x6>
			<y6>235.302903</y6>
			<x7>366.998001</x7>
			<y7>222.710399</y7>
			<x8>377.034318</x8>
			<y8>212.523562</y8>
			<x9>386.559331</x9>
			<y9>177.973096</y9>
			<x10>391.573155</x10>
			<y10>169.350578</y10>
			<x11>392.452569</x11>
			<y11>158.647402</y11>
			<x12>387.733565</x12>
			<y12>154.183786</y12>
			<x13>400.093724</x13>
			<y13>137.607527</y13>
			<x14>394.750405</x14>
			<y14>131.083385</y14>
			<x15>387.026463</x15>
			<y15>129.627456</y15>
			<x16>374.722809</x16>
			<y16>135.052164</y16>
			<x17>364.762855</x17>
			<y17>133.926235</y17>
			<x18>356.33516</x18>
			<y18>131.05464</y18>
			<x19>350.461228</x19>
			<y19>125.273601</y19>
			<x20>325.314361</x20>
			<y20>117.335163</y20>
			<x21>308.978392</x21>
			<y21>118.068283</y21>
			<x22>290.528643</x22>
			<y22>128.832018</y22>
			<x23>278.05772</x23>
			<y23>140.961007</y23>
			<x24>270.906906</x24>
			<y24>136.634692</y24>
			<x25>261.222188</x25>
			<y25>135.056602</y25>
			<x26>258.237112</x26>
			<y26>137.903075</y26>
			<x27>265.441908</x27>
			<y27>145.355451</y27>
			<x28>262.096561</x28>
			<y28>152.908651</y28>
			<x29>258.45332</x29>
			<y29>162.880078</y29>
			<x30>257.565512</x30>
			<y30>178.997814</y30>
			<x31>256.087237</x31>
			<y31>183.869541</y31>
			<x32>251.601228</x32>
			<y32>193.553809</y32>
			<x33>245.364505</x33>
			<y33>206.75711</y33>
			<x34>247.189337</x34>
			<y34>218.675682</y34>
			<x35>249.096405</x35>
			<y35>228.144539</y35>
			<x36>250.152311</x36>
			<y36>242.740796</y36>
			<x37>243.736851</x37>
			<y37>257.395034</y37>
			<x38>241.487129</x38>
			<y38>279.222061</y38>
			<x39>230.837963</x39>
			<y39>292.601716</y39>
			<x40>230.472375</x40>
			<y40>313.390909</y40>
			<x41>227.198073</x41>
			<y41>325.713808</y41>
			<x42>219.468535</x42>
			<y42>327.867586</y42>
			<x43>212.357992</x43>
			<y43>348.164356</y43>
			<x44>215.89969</x44>
			<y44>365.749375</y44>
			<x45>216.856296</x45>
			<y45>381.15171</y45>
			<x46>230.920162</x46>
			<y46>416.684444</y46>
			<x47>252.727276</x47>
			<y47>428.566374</y47>
			<x48>272.556829</x48>
			<y48>451.155265</y48>
			<x49>284.194205</x49>
			<y49>470.742831</y49>
			<x50>310.439218</x50>
			<y50>478.677485</y50>
			<x51>342.112308</x51>
			<y51>476.408954</y51>
			<x52>367.993976</x52>
			<y52>478.382428</y52>
			<x53>383.135298</x53>
			<y53>476.654316</y53>
			<x54>439.143536</x54>
			<y54>474.656434</y54>
			<x55>471.213815</x55>
			<y55>469.163599</y55>
			<x56>455.518672</x56>
			<y56>448.655365</y56>
			<x57>440.300156</x57>
			<y57>424.277967</y57>
			<x58>423.864061</x58>
			<y58>388.398887</y58>
			<x59>405.430546</x59>
			<y59>363.387983</y59>
			<x60>389.207588</x60>
			<y60>341.818001</y60>
			<x61>364.951327</x61>
			<y61>315.956973</y61>
			<x62>369.712571</x62>
			<y62>305.820547</y62>
			<x63>358.268474</x63>
			<y63>300.703293</y63>
			<x64>347.919721</x64>
			<y64>297.387107</y64>
			<x65>340.57311</x65>
			<y65>292.868091</y65>
			<x66>343.9923</x66>
			<y66>288.279737</y66>
			<x67>339.247841</x67>
			<y67>287.587044</y67>
			<x68>329.960315</x68>
			<y68>282.784652</y68>
			<x69>330.050943</x69>
			<y69>274.920377</y69>
		</polygon>
	</object>
</annotation>