<annotation>
	<folder />
	<filename>000003_JPG_jpg.rf.a3868e790f9d7c1a5f2c8acc3e5c4796.jpg</filename>
	<path>000003_JPG_jpg.rf.a3868e790f9d7c1a5f2c8acc3e5c4796.jpg</path>
	<source>
		<database>roboflow.com</database>
	</source>
	<size>
		<width>640</width>
		<height>640</height>
		<depth>3</depth>
	</size>
	<segmented>0</segmented>
	<object>
		<name>Plastic</name>
		<pose>Unspecified</pose>
		<truncated>0</truncated>
		<difficult>0</difficult>
		<occluded>0</occluded>
		<bndbox>
			<xmin>356</xmin>
			<xmax>412</xmax>
			<ymin>280</ymin>
			<ymax>324</ymax>
		</bndbox>
		<polygon>
			<x1>365.228758</x1>
			<y1>290.588235</y1>
			<x2>369.934641</x2>
			<y2>293.529412</y2>
			<x3>376.470588</x3>
			<y3>298.039216</y3>
			<x4>381.176471</x4>
			<y4>301.176471</y4>
			<x5>385.098039</x5>
			<y5>304.509804</y5>
			<x6>386.666667</x6>
			<y6>306.27451</y6>
			<x7>387.189542</x7>
			<y7>308.235294</y7>
			<x8>387.973856</x8>
			<y8>310.980392</y8>
			<x9>389.803922</x9>
			<y9>314.509804</y9>
			<x10>393.202614</x10>
			<y10>317.254902</y10>
			<x11>396.339869</x11>
			<y11>319.411765</y11>
			<x12>403.398693</x12>
			<y12>322.54902</y12>
			<x13>406.535948</x13>
			<y13>323.137255</y13>
			<x14>407.058824</x14>
			<y14>322.54902</y14>
			<x15>406.27451</x15>
			<y15>321.960784</y15>
			<x16>397.124183</x16>
			<y16>316.470588</y16>
			<x17>397.647059</x17>
			<y17>316.078431</y17>
			<x18>406.013072</x18>
			<y18>320.588235</y18>
			<x19>407.843137</x19>
			<y19>320.980392</y19>
			<x20>408.888889</x20>
			<y20>321.372549</y20>
			<x21>409.150327</x21>
			<y21>320.980392</y21>
			<x22>398.69281</x22>
			<y22>314.901961</y22>
			<x23>398.69281</x23>
			<y23>314.313725</y23>
			<x24>400</x24>
			<y24>314.901961</y24>
			<x25>401.568627</x25>
			<y25>315.882353</y25>
			<x26>403.921569</x26>
			<y26>317.254902</y26>
			<x27>406.797386</x27>
			<y27>319.019608</y27>
			<x28>408.366013</x28>
			<y28>320.196078</y28>
			<x29>410.196078</x29>
			<y29>320.784314</y29>
			<x30>410.196078</x30>
			<y30>320.196078</y30>
			<x31>408.366013</x31>
			<y31>318.627451</y31>
			<x32>406.27451</x32>
			<y32>317.254902</y32>
			<x33>403.921569</x33>
			<y33>315.686275</y33>
			<x34>401.045752</x34>
			<y34>313.72549</y34>
			<x35>401.568627</x35>
			<y35>313.333333</y35>
			<x36>403.921569</x36>
			<y36>314.901961</y36>
			<x37>407.058824</x37>
			<y37>316.470588</y37>
			<x38>409.150327</x38>
			<y38>317.843137</y38>
			<x39>410.457516</x39>
			<y39>317.45098</y39>
			<x40>410.718954</x40>
			<y40>316.470588</y40>
			<x41>408.366013</x41>
			<y41>314.509804</y41>
			<x42>403.660131</x42>
			<y42>311.372549</y42>
			<x43>400.522876</x43>
			<y43>308.823529</y43>
			<x44>394.248366</x44>
			<y44>305.098039</y44>
			<x45>388.235294</x45>
			<y45>302.54902</y45>
			<x46>385.620915</x46>
			<y46>300.588235</y46>
			<x47>374.117647</x47>
			<y47>290.980392</y47>
			<x48>368.366013</x48>
			<y48>286.27451</y48>
			<x49>357.124183</x49>
			<y49>279.411765</y49>
			<x50>355.03268</x50>
			<y50>279.803922</y50>
			<x51>354.509804</x51>
			<y51>280.784314</y51>
			<x52>356.078431</x52>
			<y52>282.745098</y52>
			<x53>360.784314</x53>
			<y53>286.666667</y53>
			<x54>365.228758</x54>
			<y54>290.588235</y54>
		</polygon>
	</object>
	<object>
		<name>Trash</name>
		<pose>Unspecified</pose>
		<truncated>0</truncated>
		<difficult>0</difficult>
		<occluded>0</occluded>
		<bndbox>
			<xmin>530</xmin>
			<xmax>542</xmax>
			<ymin>231</ymin>
			<ymax>241</ymax>
		</bndbox>
		<polygon>
			<x1>540.653595</x1>
			<y1>231.372549</y1>
			<x2>534.379085</x2>
			<y2>229.803922</y2>
			<x3>528.627451</x3>
			<y3>238.431373</y3>
			<x4>530.718954</x4>
			<y4>240.392157</y4>
			<x5>535.424837</x5>
			<y5>240.392157</y5>
			<x6>540.653595</x6>
			<y6>231.372549</y6>
		</polygon>
	</object>
</annotation>