<annotation>
	<folder />
	<filename>000020_JPG_jpg.rf.72d463a2c78e8da7537bf2829a0936f3.jpg</filename>
	<path>000020_JPG_jpg.rf.72d463a2c78e8da7537bf2829a0936f3.jpg</path>
	<source>
		<database>roboflow.com</database>
	</source>
	<size>
		<width>640</width>
		<height>640</height>
		<depth>3</depth>
	</size>
	<segmented>0</segmented>
	<object>
		<name>Cardboard</name>
		<pose>Unspecified</pose>
		<truncated>0</truncated>
		<difficult>0</difficult>
		<occluded>0</occluded>
		<bndbox>
			<xmin>431</xmin>
			<xmax>526</xmax>
			<ymin>76</ymin>
			<ymax>167</ymax>
		</bndbox>
		<polygon>
			<x1>454.379085</x1>
			<y1>107.254902</y1>
			<x2>452.54902</x2>
			<y2>106.078431</y2>
			<x3>448.366013</x3>
			<y3>103.529412</y3>
			<x4>446.27451</x4>
			<y4>102.156863</y4>
			<x5>443.660131</x5>
			<y5>101.960784</y5>
			<x6>442.875817</x6>
			<y6>101.372549</y6>
			<x7>443.137255</x7>
			<y7>99.607843</y7>
			<x8>445.490196</x8>
			<y8>96.666667</y8>
			<x9>440</x9>
			<y9>101.372549</y9>
			<x10>430.588235</x10>
			<y10>101.176471</y10>
			<x11>429.542484</x11>
			<y11>101.764706</y11>
			<x12>429.542484</x12>
			<y12>102.54902</y12>
			<x13>430.326797</x13>
			<y13>104.313725</y13>
			<x14>429.542484</x14>
			<y14>105.294118</y14>
			<x15>430.065359</x15>
			<y15>108.039216</y15>
			<x16>432.156863</x16>
			<y16>108.235294</y16>
			<x17>434.509804</x17>
			<y17>106.862745</y17>
			<x18>436.339869</x18>
			<y18>106.666667</y18>
			<x19>436.601307</x19>
			<y19>105.882353</y19>
			<x20>438.954248</x20>
			<y20>105.490196</y20>
			<x21>442.352941</x21>
			<y21>105.882353</y21>
			<x22>443.398693</x22>
			<y22>106.470588</y22>
			<x23>444.96732</x23>
			<y23>105.686275</y23>
			<x24>445.490196</x24>
			<y24>105.098039</y24>
			<x25>446.535948</x25>
			<y25>105.294118</y25>
			<x26>447.843137</x26>
			<y26>105.882353</y26>
			<x27>448.104575</x27>
			<y27>107.45098</y27>
			<x28>451.503268</x28>
			<y28>107.254902</y28>
			<x29>450.718954</x29>
			<y29>108.235294</y29>
			<x30>452.54902</x30>
			<y30>108.823529</y30>
			<x31>453.594771</x31>
			<y31>108.235294</y31>
			<x32>455.686275</x32>
			<y32>107.843137</y32>
			<x33>457.777778</x33>
			<y33>116.666667</y33>
			<x34>457.254902</x34>
			<y34>118.823529</y34>
			<x35>456.20915</x35>
			<y35>119.607843</y35>
			<x36>456.470588</x36>
			<y36>120.196078</y36>
			<x37>457.254902</x37>
			<y37>121.372549</y37>
			<x38>455.947712</x38>
			<y38>122.745098</y38>
			<x39>454.117647</x39>
			<y39>122.745098</y39>
			<x40>453.071895</x40>
			<y40>121.764706</y40>
			<x41>453.333333</x41>
			<y41>118.431373</y41>
			<x42>452.54902</x42>
			<y42>117.45098</y42>
			<x43>453.856209</x43>
			<y43>115.686275</y43>
			<x44>451.503268</x44>
			<y44>114.509804</y44>
			<x45>449.411765</x45>
			<y45>115.098039</y45>
			<x46>447.843137</x46>
			<y46>112.352941</y46>
			<x47>446.797386</x47>
			<y47>114.705882</y47>
			<x48>449.673203</x48>
			<y48>115.882353</y48>
			<x49>450.196078</x49>
			<y49>116.862745</y49>
			<x50>449.150327</x50>
			<y50>117.254902</y50>
			<x51>449.673203</x51>
			<y51>118.431373</y51>
			<x52>450.457516</x52>
			<y52>119.803922</y52>
			<x53>449.934641</x53>
			<y53>120.196078</y53>
			<x54>450.457516</x54>
			<y54>121.176471</y54>
			<x55>447.320261</x55>
			<y55>124.117647</y55>
			<x56>445.490196</x56>
			<y56>123.72549</y56>
			<x57>444.96732</x57>
			<y57>124.117647</y57>
			<x58>442.614379</x58>
			<y58>123.137255</y58>
			<x59>442.352941</x59>
			<y59>122.156863</y59>
			<x60>441.568627</x60>
			<y60>121.960784</y60>
			<x61>441.30719</x61>
			<y61>124.117647</y61>
			<x62>439.215686</x62>
			<y62>126.470588</y62>
			<x63>437.647059</x63>
			<y63>126.470588</y63>
			<x64>442.352941</x64>
			<y64>138.823529</y64>
			<x65>444.183007</x65>
			<y65>140.196078</y65>
			<x66>448.366013</x66>
			<y66>144.901961</y66>
			<x67>453.333333</x67>
			<y67>149.411765</y67>
			<x68>453.333333</x68>
			<y68>150.392157</y68>
			<x69>451.764706</x69>
			<y69>151.176471</y69>
			<x70>446.797386</x70>
			<y70>150.980392</y70>
			<x71>443.137255</x71>
			<y71>151.372549</y71>
			<x72>442.352941</x72>
			<y72>152.745098</y72>
			<x73>443.137255</x73>
			<y73>164.705882</y73>
			<x74>445.490196</x74>
			<y74>162.745098</y74>
			<x75>447.843137</x75>
			<y75>163.529412</y75>
			<x76>450.196078</x76>
			<y76>164.705882</y76>
			<x77>452.026144</x77>
			<y77>164.313725</y77>
			<x78>453.594771</x78>
			<y78>165.686275</y78>
			<x79>481.830065</x79>
			<y79>163.333333</y79>
			<x80>514.248366</x80>
			<y80>159.607843</y80>
			<x81>524.705882</x81>
			<y81>157.647059</y81>
			<x82>516.601307</x82>
			<y82>126.078431</y82>
			<x83>502.222222</x83>
			<y83>79.215686</y83>
			<x84>500.915033</x84>
			<y84>75.098039</y84>
			<x85>481.30719</x85>
			<y85>77.647059</y85>
			<x86>458.562092</x86>
			<y86>79.803922</y86>
			<x87>448.888889</x87>
			<y87>80.392157</y87>
			<x88>451.503268</x88>
			<y88>91.764706</y88>
			<x89>449.934641</x89>
			<y89>93.137255</y89>
			<x90>452.287582</x90>
			<y90>93.72549</y90>
			<x91>455.424837</x91>
			<y91>106.666667</y91>
			<x92>454.379085</x92>
			<y92>107.254902</y92>
		</polygon>
	</object>
	<object>
		<name>Cardboard</name>
		<pose>Unspecified</pose>
		<truncated>0</truncated>
		<difficult>0</difficult>
		<occluded>0</occluded>
		<bndbox>
			<xmin>252</xmin>
			<xmax>407</xmax>
			<ymin>223</ymin>
			<ymax>399</ymax>
		</bndbox>
		<polygon>
			<x1>250.718954</x1>
			<y1>271.764706</y1>
			<x2>260.130719</x2>
			<y2>272.156863</y2>
			<x3>270.065359</x3>
			<y3>271.960784</y3>
			<x4>275.555556</x4>
			<y4>271.568627</y4>
			<x5>283.137255</x5>
			<y5>270.588235</y5>
			<x6>285.490196</x6>
			<y6>289.607843</y6>
			<x7>285.751634</x7>
			<y7>290.784314</y7>
			<x8>290.718954</x8>
			<y8>292.156863</y8>
			<x9>295.424837</x9>
			<y9>295.686275</y9>
			<x10>298.039216</x10>
			<y10>299.607843</y10>
			<x11>298.823529</x11>
			<y11>304.117647</y11>
			<x12>296.993464</x12>
			<y12>308.627451</y12>
			<x13>294.379085</x13>
			<y13>311.568627</y13>
			<x14>287.320261</x14>
			<y14>315.686275</y14>
			<x15>293.856209</x15>
			<y15>314.313725</y15>
			<x16>291.24183</x16>
			<y16>320.196078</y16>
			<x17>288.104575</x17>
			<y17>325.882353</y17>
			<x18>286.27451</x18>
			<y18>328.039216</y18>
			<x19>287.843137</x19>
			<y19>329.607843</y19>
			<x20>289.411765</x20>
			<y20>331.372549</y20>
			<x21>301.176471</x21>
			<y21>338.039216</y21>
			<x22>307.189542</x22>
			<y22>340.784314</y22>
			<x23>310.849673</x23>
			<y23>342.352941</y23>
			<x24>316.601307</x24>
			<y24>345.686275</y24>
			<x25>320.522876</x25>
			<y25>348.431373</y25>
			<x26>323.398693</x26>
			<y26>350.196078</y26>
			<x27>325.228758</x27>
			<y27>350.392157</y27>
			<x28>334.901961</x28>
			<y28>345.098039</y28>
			<x29>335.424837</x29>
			<y29>345.490196</y29>
			<x30>337.254902</x30>
			<y30>346.666667</y30>
			<x31>338.562092</x31>
			<y31>346.470588</y31>
			<x32>339.346405</x32>
			<y32>345.686275</y32>
			<x33>341.437908</x33>
			<y33>345.490196</y33>
			<x34>341.437908</x34>
			<y34>348.235294</y34>
			<x35>362.614379</x35>
			<y35>353.72549</y35>
			<x36>350.065359</x36>
			<y36>381.764706</y36>
			<x37>350.065359</x37>
			<y37>383.333333</y37>
			<x38>350.849673</x38>
			<y38>384.117647</y38>
			<x39>352.156863</x39>
			<y39>384.509804</y39>
			<x40>380.915033</x40>
			<y40>392.352941</y40>
			<x41>387.189542</x41>
			<y41>394.117647</y41>
			<x42>386.405229</x42>
			<y42>392.941176</y42>
			<x43>387.45098</x43>
			<y43>391.176471</y43>
			<x44>391.895425</x44>
			<y44>390.588235</y44>
			<x45>398.69281</x45>
			<y45>389.411765</y45>
			<x46>400</x46>
			<y46>390</y46>
			<x47>400.784314</x47>
			<y47>391.176471</y47>
			<x48>401.568627</x48>
			<y48>392.54902</y48>
			<x49>398.169935</x49>
			<y49>396.078431</y49>
			<x50>395.03268</x50>
			<y50>396.27451</y50>
			<x51>396.339869</x51>
			<y51>396.666667</y51>
			<x52>401.568627</x52>
			<y52>398.235294</y52>
			<x53>402.875817</x53>
			<y53>398.039216</y53>
			<x54>404.96732</x54>
			<y54>397.058824</y54>
			<x55>406.27451</x55>
			<y55>394.117647</y55>
			<x56>405.490196</x56>
			<y56>393.529412</y56>
			<x57>405.228758</x57>
			<y57>391.372549</y57>
			<x58>404.96732</x58>
			<y58>386.470588</y58>
			<x59>403.921569</x59>
			<y59>384.313725</y59>
			<x60>402.875817</x60>
			<y60>381.764706</y60>
			<x61>402.091503</x61>
			<y61>377.647059</y61>
			<x62>402.091503</x62>
			<y62>373.529412</y62>
			<x63>402.352941</x63>
			<y63>370.196078</y63>
			<x64>401.30719</x64>
			<y64>368.627451</y64>
			<x65>399.738562</x65>
			<y65>368.039216</y65>
			<x66>384.575163</x66>
			<y66>363.529412</y66>
			<x67>375.424837</x67>
			<y67>361.176471</y67>
			<x68>374.117647</x68>
			<y68>359.607843</y68>
			<x69>374.640523</x69>
			<y69>358.627451</y69>
			<x70>375.424837</x70>
			<y70>356.862745</y70>
			<x71>377.51634</x71>
			<y71>351.568627</y71>
			<x72>379.084967</x72>
			<y72>346.862745</y72>
			<x73>378.823529</x73>
			<y73>344.901961</y73>
			<x74>373.594771</x74>
			<y74>341.176471</y74>
			<x75>376.470588</x75>
			<y75>341.176471</y75>
			<x76>375.947712</x76>
			<y76>335.098039</y76>
			<x77>373.594771</x77>
			<y77>323.137255</y77>
			<x78>371.764706</x78>
			<y78>314.901961</y78>
			<x79>360.522876</x79>
			<y79>322.352941</y79>
			<x80>360.784314</x80>
			<y80>323.921569</y80>
			<x81>352.679739</x81>
			<y81>329.215686</y81>
			<x82>352.679739</x82>
			<y82>330.392157</y82>
			<x83>350.588235</x83>
			<y83>331.764706</y83>
			<x84>348.496732</x84>
			<y84>330.980392</y84>
			<x85>345.620915</x85>
			<y85>330.784314</y85>
			<x86>340.653595</x86>
			<y86>330</y86>
			<x87>339.869281</x87>
			<y87>328.823529</y87>
			<x88>339.084967</x88>
			<y88>326.862745</y88>
			<x89>338.823529</x89>
			<y89>325.490196</y89>
			<x90>334.379085</x90>
			<y90>322.745098</y90>
			<x91>335.163399</x91>
			<y91>321.372549</y91>
			<x92>335.686275</x92>
			<y92>319.803922</y92>
			<x93>334.640523</x93>
			<y93>318.431373</y93>
			<x94>334.640523</x94>
			<y94>317.254902</y94>
			<x95>338.039216</x95>
			<y95>317.254902</y95>
			<x96>341.437908</x96>
			<y96>317.058824</y96>
			<x97>339.084967</x97>
			<y97>313.72549</y97>
			<x98>338.300654</x98>
			<y98>311.568627</y98>
			<x99>338.562092</x99>
			<y99>311.176471</y99>
			<x100>340.915033</x100>
			<y100>310.980392</y100>
			<x101>343.006536</x101>
			<y101>310.588235</y101>
			<x102>345.359477</x102>
			<y102>311.568627</y102>
			<x103>348.235294</x103>
			<y103>313.333333</y103>
			<x104>348.496732</x104>
			<y104>317.45098</y104>
			<x105>346.666667</x105>
			<y105>317.45098</y105>
			<x106>344.575163</x106>
			<y106>320.588235</y106>
			<x107>345.882353</x107>
			<y107>321.960784</y107>
			<x108>351.372549</x108>
			<y108>318.627451</y108>
			<x109>353.986928</x109>
			<y109>316.666667</y109>
			<x110>358.431373</x110>
			<y110>312.156863</y110>
			<x111>361.830065</x111>
			<y111>311.372549</y111>
			<x112>364.705882</x112>
			<y112>311.960784</y112>
			<x113>371.764706</x113>
			<y113>313.137255</y113>
			<x114>370.196078</x114>
			<y114>305.686275</y114>
			<x115>369.150327</x115>
			<y115>301.568627</y115>
			<x116>343.267974</x116>
			<y116>286.666667</y116>
			<x117>343.267974</x117>
			<y117>287.843137</y117>
			<x118>344.313725</x118>
			<y118>290.784314</y118>
			<x119>344.836601</x119>
			<y119>294.117647</y119>
			<x120>343.006536</x120>
			<y120>296.470588</y120>
			<x121>340.130719</x121>
			<y121>298.235294</y121>
			<x122>336.20915</x122>
			<y122>299.019608</y122>
			<x123>333.856209</x123>
			<y123>297.843137</y123>
			<x124>330.196078</x124>
			<y124>296.862745</y124>
			<x125>328.104575</x125>
			<y125>297.647059</y125>
			<x126>327.581699</x126>
			<y126>296.862745</y126>
			<x127>327.581699</x127>
			<y127>296.078431</y127>
			<x128>326.535948</x128>
			<y128>295.294118</y128>
			<x129>324.183007</x129>
			<y129>295.490196</y129>
			<x130>320.522876</x130>
			<y130>294.901961</y130>
			<x131>317.385621</x131>
			<y131>293.921569</y131>
			<x132>316.862745</x132>
			<y132>293.137255</y132>
			<x133>316.339869</x133>
			<y133>292.352941</y133>
			<x134>315.03268</x134>
			<y134>292.156863</y134>
			<x135>314.771242</x135>
			<y135>293.137255</y135>
			<x136>313.464052</x136>
			<y136>293.529412</y136>
			<x137>312.418301</x137>
			<y137>292.745098</y137>
			<x138>311.633987</x138>
			<y138>291.176471</y138>
			<x139>311.372549</x139>
			<y139>288.627451</y139>
			<x140>312.418301</x140>
			<y140>287.45098</y140>
			<x141>315.555556</x141>
			<y141>286.666667</y141>
			<x142>317.647059</x142>
			<y142>284.705882</y142>
			<x143>317.385621</x143>
			<y143>282.745098</y143>
			<x144>317.908497</x144>
			<y144>280.392157</y144>
			<x145>321.045752</x145>
			<y145>278.039216</y145>
			<x146>323.398693</x146>
			<y146>277.058824</y146>
			<x147>325.751634</x147>
			<y147>276.27451</y147>
			<x148>328.366013</x148>
			<y148>277.058824</y148>
			<x149>331.503268</x149>
			<y149>279.215686</y149>
			<x150>331.503268</x150>
			<y150>280</y150>
			<x151>333.071895</x151>
			<y151>280.980392</y151>
			<x152>333.333333</x152>
			<y152>282.745098</y152>
			<x153>335.424837</x153>
			<y153>282.941176</y153>
			<x154>337.254902</x154>
			<y154>282.156863</y154>
			<x155>343.006536</x155>
			<y155>285.686275</y155>
			<x156>340.130719</x156>
			<y156>282.54902</y156>
			<x157>352.941176</x157>
			<y157>282.941176</y157>
			<x158>366.27451</x158>
			<y158>283.333333</y158>
			<x159>368.104575</x159>
			<y159>280.980392</y159>
			<x160>372.287582</x160>
			<y160>275.098039</y160>
			<x161>372.026144</x161>
			<y161>271.176471</y161>
			<x162>370.457516</x162>
			<y162>269.215686</y162>
			<x163>369.411765</x163>
			<y163>267.254902</y163>
			<x164>365.751634</x164>
			<y164>263.72549</y164>
			<x165>364.705882</x165>
			<y165>262.941176</y165>
			<x166>370.457516</x166>
			<y166>258.039216</y166>
			<x167>373.071895</x167>
			<y167>255.294118</y167>
			<x168>374.640523</x168>
			<y168>252.54902</y168>
			<x169>374.117647</x169>
			<y169>229.607843</y169>
			<x170>372.287582</x170>
			<y170>228.627451</y170>
			<x171>364.444444</x171>
			<y171>228.431373</y171>
			<x172>363.398693</x172>
			<y172>227.843137</y172>
			<x173>362.875817</x173>
			<y173>222.54902</y173>
			<x174>361.30719</x174>
			<y174>221.764706</y174>
			<x175>344.575163</x175>
			<y175>222.156863</y175>
			<x176>349.542484</x176>
			<y176>225.490196</y176>
			<x177>349.281046</x177>
			<y177>227.254902</y177>
			<x178>348.235294</x178>
			<y178>229.803922</y178>
			<x179>348.235294</x179>
			<y179>231.568627</y179>
			<x180>346.666667</x180>
			<y180>231.764706</y180>
			<x181>346.143791</x181>
			<y181>230.980392</y181>
			<x182>344.052288</x182>
			<y182>232.745098</y182>
			<x183>337.777778</x183>
			<y183>234.509804</y183>
			<x184>334.379085</x184>
			<y184>236.078431</y184>
			<x185>330.718954</x185>
			<y185>236.666667</y185>
			<x186>329.673203</x186>
			<y186>235.098039</y186>
			<x187>330.980392</x187>
			<y187>233.72549</y187>
			<x188>331.24183</x188>
			<y188>232.352941</y188>
			<x189>334.117647</x189>
			<y189>229.019608</y189>
			<x190>339.084967</x190>
			<y190>226.862745</y190>
			<x191>336.20915</x191>
			<y191>224.509804</y191>
			<x192>335.424837</x192>
			<y192>222.352941</y192>
			<x193>324.444444</x193>
			<y193>222.352941</y193>
			<x194>310.588235</x194>
			<y194>228.039216</y194>
			<x195>311.895425</x195>
			<y195>229.019608</y195>
			<x196>304.052288</x196>
			<y196>235.294118</y196>
			<x197>281.830065</x197>
			<y197>250.784314</y197>
			<x198>280.784314</x198>
			<y198>251.176471</y198>
			<x199>276.339869</x199>
			<y199>254.313725</y199>
			<x200>276.078431</x200>
			<y200>255.490196</y200>
			<x201>264.575163</x201>
			<y201>260.980392</y201>
			<x202>261.437908</x202>
			<y202>263.529412</y202>
			<x203>257.254902</x203>
			<y203>264.705882</y203>
			<x204>256.20915</x204>
			<y204>267.254902</y204>
			<x205>254.901961</x205>
			<y205>269.019608</y205>
			<x206>254.640523</x206>
			<y206>269.803922</y206>
			<x207>250.718954</x207>
			<y207>271.764706</y207>
		</polygon>
	</object>
	<object>
		<name>Plastic</name>
		<pose>Unspecified</pose>
		<truncated>0</truncated>
		<difficult>0</difficult>
		<occluded>0</occluded>
		<bndbox>
			<xmin>249</xmin>
			<xmax>300</xmax>
			<ymin>272</ymin>
			<ymax>317</ymax>
		</bndbox>
		<polygon>
			<x1>263.79085</x1>
			<y1>279.215686</y1>
			<x2>268.75817</x2>
			<y2>281.764706</y2>
			<x3>273.986928</x3>
			<y3>284.509804</y3>
			<x4>279.477124</x4>
			<y4>287.843137</y4>
			<x5>281.830065</x5>
			<y5>288.627451</y5>
			<x6>281.30719</x6>
			<y6>290</y6>
			<x7>277.647059</x7>
			<y7>291.372549</y7>
			<x8>276.601307</x8>
			<y8>292.941176</y8>
			<x9>271.895425</x9>
			<y9>293.72549</y9>
			<x10>265.098039</x10>
			<y10>295.882353</y10>
			<x11>257.254902</x11>
			<y11>296.470588</y11>
			<x12>249.411765</x12>
			<y12>296.862745</y12>
			<x13>278.169935</x13>
			<y13>310.196078</y13>
			<x14>278.954248</x14>
			<y14>312.941176</y14>
			<x15>277.124183</x15>
			<y15>314.509804</y15>
			<x16>278.69281</x16>
			<y16>315.686275</y16>
			<x17>281.045752</x17>
			<y17>315.490196</y17>
			<x18>285.490196</x18>
			<y18>315.490196</y18>
			<x19>290.457516</x19>
			<y19>314.901961</y19>
			<x20>294.379085</x20>
			<y20>312.941176</y20>
			<x21>294.901961</x21>
			<y21>310.588235</y21>
			<x22>296.993464</x22>
			<y22>308.235294</y22>
			<x23>298.562092</x23>
			<y23>304.313725</y23>
			<x24>298.562092</x24>
			<y24>301.176471</y24>
			<x25>297.51634</x25>
			<y25>298.235294</y25>
			<x26>295.424837</x26>
			<y26>295.490196</y26>
			<x27>292.54902</x27>
			<y27>293.529412</y27>
			<x28>289.673203</x28>
			<y28>291.960784</y28>
			<x29>285.751634</x29>
			<y29>290.588235</y29>
			<x30>285.228758</x30>
			<y30>290</y30>
			<x31>284.183007</x31>
			<y31>279.607843</y31>
			<x32>283.398693</x32>
			<y32>271.176471</y32>
			<x33>280.261438</x33>
			<y33>270.980392</y33>
			<x34>276.078431</x34>
			<y34>271.568627</y34>
			<x35>266.928105</x35>
			<y35>272.156863</y35>
			<x36>263.006536</x36>
			<y36>272.352941</y36>
			<x37>259.607843</x37>
			<y37>272.156863</y37>
			<x38>250.980392</x38>
			<y38>271.764706</y38>
			<x39>248.104575</x39>
			<y39>273.333333</y39>
			<x40>255.686275</x40>
			<y40>273.72549</y40>
			<x41>256.20915</x41>
			<y41>274.901961</y41>
			<x42>261.960784</x42>
			<y42>275.490196</y42>
			<x43>264.313725</x43>
			<y43>276.862745</y43>
			<x44>263.79085</x44>
			<y44>279.215686</y44>
		</polygon>
	</object>
	<object>
		<name>Trash</name>
		<pose>Unspecified</pose>
		<truncated>0</truncated>
		<difficult>0</difficult>
		<occluded>0</occluded>
		<bndbox>
			<xmin>325</xmin>
			<xmax>463</xmax>
			<ymin>481</ymin>
			<ymax>566</ymax>
		</bndbox>
		<polygon>
			<x1>359.738562</x1>
			<y1>485.490196</y1>
			<x2>356.078431</x2>
			<y2>486.27451</y2>
			<x3>352.679739</x3>
			<y3>484.901961</y3>
			<x4>350.065359</x4>
			<y4>484.705882</y4>
			<x5>348.235294</x5>
			<y5>483.921569</y5>
			<x6>346.928105</x6>
			<y6>482.54902</y6>
			<x7>345.359477</x7>
			<y7>480.392157</y7>
			<x8>327.320261</x8>
			<y8>480.196078</y8>
			<x9>326.797386</x9>
			<y9>481.960784</y9>
			<x10>327.058824</x10>
			<y10>495.490196</y10>
			<x11>326.27451</x11>
			<y11>511.568627</y11>
			<x12>324.96732</x12>
			<y12>512.745098</y12>
			<x13>326.27451</x13>
			<y13>515.294118</y13>
			<x14>327.058824</x14>
			<y14>527.45098</y14>
			<x15>327.320261</x15>
			<y15>530</y15>
			<x16>326.27451</x16>
			<y16>533.72549</y16>
			<x17>326.013072</x17>
			<y17>539.607843</y17>
			<x18>325.490196</x18>
			<y18>547.45098</y18>
			<x19>324.444444</x19>
			<y19>553.333333</y19>
			<x20>327.843137</x20>
			<y20>553.333333</y20>
			<x21>341.960784</x21>
			<y21>554.117647</y21>
			<x22>354.771242</x22>
			<y22>554.705882</y22>
			<x23>361.045752</x23>
			<y23>554.901961</y23>
			<x24>360</x24>
			<y24>553.137255</y24>
			<x25>361.30719</x25>
			<y25>553.137255</y25>
			<x26>364.444444</x26>
			<y26>552.745098</y26>
			<x27>365.228758</x27>
			<y27>552.156863</y27>
			<x28>367.058824</x28>
			<y28>551.960784</y28>
			<x29>367.843137</x29>
			<y29>552.54902</y29>
			<x30>369.673203</x30>
			<y30>554.313725</y30>
			<x31>369.934641</x31>
			<y31>555.294118</y31>
			<x32>373.071895</x32>
			<y32>555.490196</y32>
			<x33>375.686275</x33>
			<y33>554.901961</y33>
			<x34>383.267974</x34>
			<y34>559.019608</y34>
			<x35>390.849673</x35>
			<y35>563.137255</y35>
			<x36>392.679739</x36>
			<y36>564.313725</y36>
			<x37>397.124183</x37>
			<y37>565.294118</y37>
			<x38>402.614379</x38>
			<y38>565.098039</y38>
			<x39>404.705882</x39>
			<y39>565.294118</y39>
			<x40>409.411765</x40>
			<y40>565.294118</y40>
			<x41>410.457516</x41>
			<y41>564.313725</y41>
			<x42>414.640523</x42>
			<y42>563.72549</y42>
			<x43>415.686275</x43>
			<y43>563.333333</y43>
			<x44>423.006536</x44>
			<y44>563.137255</y44>
			<x45>424.313725</x45>
			<y45>562.54902</y45>
			<x46>427.712418</x46>
			<y46>562.352941</y46>
			<x47>431.111111</x47>
			<y47>561.568627</y47>
			<x48>431.111111</x48>
			<y48>560.784314</y48>
			<x49>432.679739</x49>
			<y49>558.823529</y49>
			<x50>435.03268</x50>
			<y50>558.823529</y50>
			<x51>435.294118</x51>
			<y51>556.470588</y51>
			<x52>455.163399</x52>
			<y52>557.843137</y52>
			<x53>454.901961</x53>
			<y53>554.117647</y53>
			<x54>456.732026</x54>
			<y54>552.54902</y54>
			<x55>457.254902</x55>
			<y55>550.588235</y55>
			<x56>461.437908</x56>
			<y56>547.647059</y56>
			<x57>460.915033</x57>
			<y57>539.803922</y57>
			<x58>460.130719</x58>
			<y58>535.490196</y58>
			<x59>459.607843</x59>
			<y59>534.117647</y59>
			<x60>461.437908</x60>
			<y60>525.686275</y60>
			<x61>461.960784</x61>
			<y61>522.745098</y61>
			<x62>461.960784</x62>
			<y62>511.960784</y62>
			<x63>461.176471</x63>
			<y63>497.843137</y63>
			<x64>460.653595</x64>
			<y64>494.901961</y64>
			<x65>458.823529</x65>
			<y65>483.921569</y65>
			<x66>396.862745</x66>
			<y66>481.764706</y66>
			<x67>367.320261</x67>
			<y67>480.784314</y67>
			<x68>366.797386</x68>
			<y68>482.352941</y68>
			<x69>364.96732</x69>
			<y69>482.745098</y69>
			<x70>363.660131</x70>
			<y70>485.098039</y70>
			<x71>359.738562</x71>
			<y71>485.490196</y71>
		</polygon>
	</object>
	<object>
		<name>Trash</name>
		<pose>Unspecified</pose>
		<truncated>0</truncated>
		<difficult>0</difficult>
		<occluded>0</occluded>
		<bndbox>
			<xmin>471</xmin>
			<xmax>496</xmax>
			<ymin>518</ymin>
			<ymax>539</ymax>
		</bndbox>
		<polygon>
			<x1>476.078431</x1>
			<y1>524.313725</y1>
			<x2>477.647059</x2>
			<y2>525.686275</y2>
			<x3>478.431373</x3>
			<y3>526.27451</y3>
			<x4>480.522876</x4>
			<y4>526.27451</y4>
			<x5>482.352941</x5>
			<y5>526.862745</y5>
			<x6>483.398693</x6>
			<y6>528.039216</y6>
			<x7>482.091503</x7>
			<y7>529.803922</y7>
			<x8>479.738562</x8>
			<y8>529.803922</y8>
			<x9>475.816993</x9>
			<y9>529.215686</y9>
			<x10>472.679739</x10>
			<y10>527.45098</y10>
			<x11>470.849673</x11>
			<y11>527.45098</y11>
			<x12>471.372549</x12>
			<y12>528.039216</y12>
			<x13>477.124183</x13>
			<y13>530.980392</y13>
			<x14>480.784314</x14>
			<y14>532.54902</y14>
			<x15>483.137255</x15>
			<y15>532.54902</y15>
			<x16>483.398693</x16>
			<y16>533.72549</y16>
			<x17>485.228758</x17>
			<y17>534.901961</y17>
			<x18>487.320261</x18>
			<y18>534.901961</y18>
			<x19>489.150327</x19>
			<y19>534.117647</y19>
			<x20>489.150327</x20>
			<y20>537.058824</y20>
			<x21>491.24183</x21>
			<y21>538.431373</y21>
			<x22>492.54902</x22>
			<y22>538.431373</y22>
			<x23>494.117647</x23>
			<y23>534.705882</y23>
			<x24>494.901961</x24>
			<y24>533.921569</y24>
			<x25>494.640523</x25>
			<y25>530</y25>
			<x26>495.163399</x26>
			<y26>522.352941</y26>
			<x27>494.379085</x27>
			<y27>521.372549</y27>
			<x28>489.411765</x28>
			<y28>519.019608</y28>
			<x29>486.27451</x29>
			<y29>518.235294</y29>
			<x30>483.660131</x30>
			<y30>516.666667</y30>
			<x31>479.738562</x31>
			<y31>519.411765</y31>
			<x32>479.477124</x32>
			<y32>520.392157</y32>
			<x33>469.803922</x33>
			<y33>523.529412</y33>
			<x34>470.588235</x34>
			<y34>525.098039</y34>
			<x35>471.372549</x35>
			<y35>525.294118</y35>
			<x36>472.679739</x36>
			<y36>525.686275</y36>
			<x37>473.986928</x37>
			<y37>524.705882</y37>
			<x38>476.078431</x38>
			<y38>524.313725</y38>
		</polygon>
	</object>
	<object>
		<name>Trash</name>
		<pose>Unspecified</pose>
		<truncated>0</truncated>
		<difficult>0</difficult>
		<occluded>0</occluded>
		<bndbox>
			<xmin>329</xmin>
			<xmax>348</xmax>
			<ymin>606</ymin>
			<ymax>616</ymax>
		</bndbox>
		<polygon>
			<x1>346.666667</x1>
			<y1>605.490196</y1>
			<x2>328.366013</x2>
			<y2>611.372549</y2>
			<x3>328.366013</x3>
			<y3>615.294118</y3>
			<x4>346.666667</x4>
			<y4>611.372549</y4>
			<x5>346.666667</x5>
			<y5>605.490196</y5>
		</polygon>
	</object>
	<object>
		<name>Trash</name>
		<pose>Unspecified</pose>
		<truncated>0</truncated>
		<difficult>0</difficult>
		<occluded>0</occluded>
		<bndbox>
			<xmin>320</xmin>
			<xmax>333</xmax>
			<ymin>121</ymin>
			<ymax>134</ymax>
		</bndbox>
		<polygon>
			<x1>325.751634</x1>
			<y1>119.607843</y1>
			<x2>318.954248</x2>
			<y2>120.392157</y2>
			<x3>324.183007</x3>
			<y3>131.764706</y3>
			<x4>328.888889</x4>
			<y4>132.54902</y4>
			<x5>331.503268</x5>
			<y5>131.764706</y5>
			<x6>325.751634</x6>
			<y6>119.607843</y6>
		</polygon>
	</object>
</annotation>