<annotation>
	<folder />
	<filename>000069_jpg.rf.5531b2ba278bf36ced8f77f1c9534715.jpg</filename>
	<path>000069_jpg.rf.5531b2ba278bf36ced8f77f1c9534715.jpg</path>
	<source>
		<database>roboflow.com</database>
	</source>
	<size>
		<width>640</width>
		<height>640</height>
		<depth>3</depth>
	</size>
	<segmented>0</segmented>
	<object>
		<name>Trash</name>
		<pose>Unspecified</pose>
		<truncated>0</truncated>
		<difficult>0</difficult>
		<occluded>0</occluded>
		<bndbox>
			<xmin>77</xmin>
			<xmax>101</xmax>
			<ymin>332</ymin>
			<ymax>381</ymax>
		</bndbox>
		<polygon>
			<x1>78.515955</x1>
			<y1>342.186358</y1>
			<x2>76.193867</x2>
			<y2>350.020427</y2>
			<x3>76.165426</x3>
			<y3>360.34285</y3>
			<x4>81.798796</x4>
			<y4>371.732005</y4>
			<x5>82.968849</x5>
			<y5>379.663239</y5>
			<x6>86.967252</x6>
			<y6>377.425724</y6>
			<x7>85.934085</x7>
			<y7>373.305575</y7>
			<x8>92.368198</x8>
			<y8>373.162589</y8>
			<x9>97.1699</x9>
			<y9>370.095047</y9>
			<x10>99.714125</x10>
			<y10>360.713942</y10>
			<x11>96.736048</x11>
			<y11>339.17016</y11>
			<x12>94.597372</x12>
			<y12>338.580286</y12>
			<x13>96.955564</x13>
			<y13>352.530151</y13>
			<x14>98.187604</x14>
			<y14>361.220776</y14>
			<x15>96.260711</x15>
			<y15>367.493682</y15>
			<x16>90.18562</x16>
			<y16>369.900717</y16>
			<x17>83.361489</x17>
			<y17>367.399959</y17>
			<x18>78.495246</x18>
			<y18>359.00599</y18>
			<x19>78.5056</x19>
			<y19>350.596174</y19>
			<x20>80.241349</x20>
			<y20>346.250001</y20>
			<x21>84.066696</x21>
			<y21>344.02661</y21>
			<x22>89.436649</x22>
			<y22>339.383779</y22>
			<x23>92.618846</x23>
			<y23>335.683985</y23>
			<x24>96.439014</x24>
			<y24>337.665503</y24>
			<x25>99.913069</x25>
			<y25>339.675274</y25>
			<x26>99.324176</x26>
			<y26>332.461053</y26>
			<x27>93.458314</x27>
			<y27>331.028749</y27>
			<x28>86.215726</x28>
			<y28>336.206667</y28>
			<x29>78.515955</x29>
			<y29>342.186358</y29>
		</polygon>
	</object>
</annotation>