<annotation>
	<folder />
	<filename>IMG_4996_JPG_jpg.rf.5740273a7236c2fba7472f7d41b4a32f.jpg</filename>
	<path>IMG_4996_JPG_jpg.rf.5740273a7236c2fba7472f7d41b4a32f.jpg</path>
	<source>
		<database>roboflow.com</database>
	</source>
	<size>
		<width>640</width>
		<height>640</height>
		<depth>3</depth>
	</size>
	<segmented>0</segmented>
	<object>
		<name>Plastic</name>
		<pose>Unspecified</pose>
		<truncated>0</truncated>
		<difficult>0</difficult>
		<occluded>0</occluded>
		<bndbox>
			<xmin>282</xmin>
			<xmax>451</xmax>
			<ymin>259</ymin>
			<ymax>345</ymax>
		</bndbox>
		<polygon>
			<x1>430.843691</x1>
			<y1>302.332136</y1>
			<x2>431.975713</x2>
			<y2>303.973515</y2>
			<x3>433.122324</x3>
			<y3>305.893525</y3>
			<x4>434.793489</x4>
			<y4>305.84486</y4>
			<x5>435.570708</x5>
			<y5>304.705997</y5>
			<x6>436.168214</x6>
			<y6>304.130482</y6>
			<x7>437.421586</x7>
			<y7>304.093984</y7>
			<x8>445.748226</x8>
			<y8>303.293392</y8>
			<x9>447.390209</x9>
			<y9>302.687461</y9>
			<x10>448.390914</x10>
			<y10>301.821149</y10>
			<x11>449.4692</x11>
			<y11>298.44106</y11>
			<x12>449.862435</x12>
			<y12>293.964692</y12>
			<x13>449.852473</x13>
			<y13>289.779122</y13>
			<x14>449.380944</x14>
			<y14>284.769822</y14>
			<x15>448.671342</x15>
			<y15>279.209339</y15>
			<x16>447.64608</x16>
			<y16>275.61145</y16>
			<x17>446.188438</x17>
			<y17>271.747094</y17>
			<x18>444.638626</x18>
			<y18>270.117882</y18>
			<x19>435.267509</x19>
			<y19>270.948891</y19>
			<x20>432.537277</x20>
			<y20>270.749339</y20>
			<x21>431.852228</x21>
			<y21>269.65306</y21>
			<x22>430.79316</x22>
			<y22>269.404843</y22>
			<x23>429.61274</x23>
			<y23>270.834503</y23>
			<x24>429.044417</x24>
			<y24>271.967284</y24>
			<x25>428.505274</x25>
			<y25>273.657328</y25>
			<x26>426.207423</x26>
			<y26>273.724242</y26>
			<x27>425.119173</x27>
			<y27>272.918761</y27>
			<x28>423.55477</x28>
			<y28>271.010916</y28>
			<x29>419.828459</x29>
			<y29>267.770741</y29>
			<x30>417.190397</x30>
			<y30>265.336047</y30>
			<x31>413.94024</x31>
			<y31>263.198235</y31>
			<x32>411.345949</x32>
			<y32>261.599439</y32>
			<x33>407.483696</x33>
			<y33>259.758509</y33>
			<x34>403.247423</x34>
			<y34>258.765643</y34>
			<x35>399.681609</x35>
			<y35>258.590425</y35>
			<x36>395.906899</x36>
			<y36>258.421289</y36>
			<x37>392.996952</x37>
			<y37>258.785087</y37>
			<x38>388.848223</x38>
			<y38>259.464015</y38>
			<x39>359.70036</x39>
			<y39>266.173025</y39>
			<x40>352.865171</x40>
			<y40>267.4883</y40>
			<x41>350.16412</x41>
			<y41>267.846013</y41>
			<x42>348.522137</x42>
			<y42>268.451943</y42>
			<x43>346.491545</x43>
			<y43>269.627306</y43>
			<x44>343.683732</x44>
			<y44>271.94153</y44>
			<x45>339.710091</x45>
			<y45>275.964047</y45>
			<x46>336.946051</x46>
			<y46>279.114169</y46>
			<x47>333.76422</x47>
			<y47>282.276456</y47>
			<x48>331.898751</x48>
			<y48>282.609837</y48>
			<x49>329.809796</x49>
			<y49>282.670669</y49>
			<x50>327.332231</x50>
			<y50>283.300932</y50>
			<x51>325.214095</x51>
			<y51>282.8045</y51>
			<x52>322.051481</x52>
			<y52>282.338481</y52>
			<x53>319.306657</x53>
			<y53>281.860298</y53>
			<x54>315.084976</x54>
			<y54>281.146064</y54>
			<x55>311.684285</x55>
			<y55>280.128866</y55>
			<x56>308.521671</x56>
			<y56>279.662848</y56>
			<x57>303.493588</x57>
			<y57>279.530213</y57>
			<x58>300.554461</x58>
			<y58>279.336745</y58>
			<x59>295.808226</x59>
			<y59>280.591188</y59>
			<x60>291.091173</x60>
			<y60>282.402896</y60>
			<x61>287.656675</x61>
			<y61>284.73537</y61>
			<x62>285.655265</x62>
			<y62>286.467996</y62>
			<x63>284.518617</x63>
			<y63>288.733554</y63>
			<x64>283.82894</x64>
			<y64>291.544211</y64>
			<x65>284.154561</x65>
			<y65>293.767187</y65>
			<x66>284.941745</x66>
			<y66>296.813894</y66>
			<x67>286.146719</x67>
			<y67>299.848435</y67>
			<x68>283.815061</x68>
			<y68>303.265023</y68>
			<x69>282.425745</x69>
			<y69>304.700767</y69>
			<x70>281.750661</x70>
			<y70>307.790057</y70>
			<x71>281.391232</x71>
			<y71>308.916753</y71>
			<x72>281.313653</x72>
			<y72>311.430528</y72>
			<x73>281.415788</x73>
			<y73>313.380955</y73>
			<x74>281.338207</x74>
			<y74>315.89473</y74>
			<x75>282.081618</x75>
			<y75>318.105539</y75>
			<x76>283.422535</x76>
			<y76>319.740835</y76>
			<x77>285.390139</x77>
			<y77>321.357881</y77>
			<x78>288.878373</x78>
			<y78>324.046875</y78>
			<x79>289.981214</x79>
			<y79>325.130989</y79>
			<x80>289.141005</x80>
			<y80>329.062259</y80>
			<x81>288.674816</x81>
			<y81>332.145466</y81>
			<x82>288.402932</x82>
			<y82>334.943956</y82>
			<x83>289.413601</x83>
			<y83>338.263212</y83>
			<x84>291.410386</x84>
			<y84>340.437524</y84>
			<x85>293.377989</x85>
			<y85>342.054569</y85>
			<x86>296.807861</x86>
			<y86>343.629033</y86>
			<x87>303.730594</x87>
			<y87>343.985554</y87>
			<x88>309.982869</x88>
			<y88>343.524425</y88>
			<x89>314.714512</x89>
			<y89>341.99135</y89>
			<x90>318.387087</x90>
			<y90>340.210058</y90>
			<x91>323.045778</x91>
			<y91>337.28382</y91>
			<x92>325.86818</x92>
			<y92>335.248229</y92>
			<x93>330.079898</x93>
			<y93>331.776892</y93>
			<x94>333.57276</x94>
			<y94>330.55895</y94>
			<x95>337.230745</x95>
			<y95>328.499025</y95>
			<x96>337.872022</x96>
			<y96>328.759407</y96>
			<x97>340.42254</x97>
			<y97>329.522307</y97>
			<x98>344.255611</x98>
			<y98>330.805972</y98>
			<x99>348.521066</x99>
			<y99>332.356103</y99>
			<x100>355.351628</x100>
			<y100>334.947765</y100>
			<x101>358.096452</x101>
			<y101>335.42595</y101>
			<x102>360.199997</x102>
			<y102>335.643749</y102>
			<x103>362.677562</x103>
			<y103>335.013486</y103>
			<x104>402.207212</x104>
			<y104>330.792725</y104>
			<x105>403.222508</x105>
			<y105>330.205043</y105>
			<x106>404.344566</x106>
			<y106>327.660853</y106>
			<x107>407.181559</x107>
			<y107>325.903895</y107>
			<x108>417.125625</x108>
			<y108>320.03317</y108>
			<x109>418.88896</x109>
			<y109>317.749361</y109>
			<x110>422.401038</x110>
			<y110>312.903113</y110>
			<x111>424.897821</x111>
			<y111>308.644545</y111>
			<x112>427.005993</x112>
			<y112>304.955408</y112>
			<x113>428.142641</x113>
			<y113>302.68985</y113>
			<x114>430.843691</x114>
			<y114>302.332136</y114>
		</polygon>
	</object>
	<object>
		<name>Plastic</name>
		<pose>Unspecified</pose>
		<truncated>0</truncated>
		<difficult>0</difficult>
		<occluded>0</occluded>
		<bndbox>
			<xmin>434</xmin>
			<xmax>451</xmax>
			<ymin>271</ymin>
			<ymax>305</ymax>
		</bndbox>
		<polygon>
			<x1>449.440019</x1>
			<y1>297.883796</y1>
			<x2>449.906207</x2>
			<y2>294.800589</y2>
			<x3>449.896244</x3>
			<y3>290.615018</y3>
			<x4>449.497669</x4>
			<y4>286.998881</y4>
			<x5>449.040733</x5>
			<y5>282.268212</y5>
			<x6>448.404083</x6>
			<y6>278.100892</y6>
			<x7>447.631489</x7>
			<y7>275.332817</y7>
			<x8>446.650001</x8>
			<y8>272.570825</y8>
			<x9>445.309085</x9>
			<y9>270.93553</y9>
			<x10>444.206245</x10>
			<y10>269.851416</y10>
			<x11>438.804142</x11>
			<y11>270.566844</y11>
			<x12>434.835128</x12>
			<y12>270.682424</y12>
			<x13>434.160044</x13>
			<y13>273.771713</y13>
			<x14>433.650082</x14>
			<y14>276.019023</y14>
			<x15>433.315208</x15>
			<y15>281.609921</y15>
			<x16>433.534068</x16>
			<y16>285.789408</y16>
			<x17>434.063957</x17>
			<y17>291.913238</y17>
			<x18>435.162171</x18>
			<y18>296.90429</y18>
			<x19>436.46928</x19>
			<y19>301.889257</y19>
			<x20>437.630482</x20>
			<y20>304.087901</y20>
			<x21>447.390209</x21>
			<y21>302.687461</y21>
			<x22>448.182019</x22>
			<y22>301.827232</y22>
			<x23>448.541447</x23>
			<y23>300.700535</y23>
			<x24>449.440019</x24>
			<y24>297.883796</y24>
		</polygon>
	</object>
	<object>
		<name>Metal</name>
		<pose>Unspecified</pose>
		<truncated>0</truncated>
		<difficult>0</difficult>
		<occluded>0</occluded>
		<bndbox>
			<xmin>9</xmin>
			<xmax>94</xmax>
			<ymin>261</ymin>
			<ymax>436</ymax>
		</bndbox>
		<polygon>
			<x1>30.17926</x1>
			<y1>266.0019</y1>
			<x2>27.852229</x2>
			<y2>265.51155</y2>
			<x3>24.660433</x3>
			<y3>264.488268</y3>
			<x4>20.603875</x4>
			<y4>262.932053</y4>
			<x5>14.04057</x5>
			<y5>261.448838</y5>
			<x6>7.895056</x6>
			<y6>259.953457</y6>
			<x7>9.460171</x7>
			<y7>273.860745</y7>
			<x8>13.819928</x8>
			<y8>309.174066</y8>
			<x9>20.561164</x9>
			<y9>361.998649</y9>
			<x10>23.579294</x10>
			<y10>383.67723</y10>
			<x11>24.716654</x11>
			<y11>393.411116</y11>
			<x12>26.048317</x12>
			<y12>402.860286</y12>
			<x13>26.801693</x13>
			<y13>409.256666</y13>
			<x14>27.588877</x14>
			<y14>412.303373</y14>
			<x15>31.339742</x15>
			<y15>420.00775</y15>
			<x16>35.003066</x16>
			<y16>426.040333</y16>
			<x17>35.314096</x17>
			<y17>427.984677</y17>
			<x18>36.50448</x18>
			<y18>430.740585</y18>
			<x19>39.545742</x19>
			<y19>432.88448</y19>
			<x20>42.319746</x20>
			<y20>433.919929</y20>
			<x21>45.914741</x21>
			<y21>434.652413</y21>
			<x22>49.883756</x22>
			<y22>434.536832</y22>
			<x23>53.44957</x23>
			<y23>434.712049</y23>
			<x24>58.239576</x24>
			<y24>434.293504</y24>
			<x25>64.448079</x25>
			<y25>432.996479</y25>
			<x26>68.985418</x26>
			<y26>431.748119</y26>
			<x27>72.49287</x27>
			<y27>430.808809</y27>
			<x28>76.583235</x28>
			<y28>429.01535</y28>
			<x29>81.688898</x29>
			<y29>426.634211</y29>
			<x30>87.736904</x30>
			<y30>422.272229</y30>
			<x31>89.529419</x31>
			<y31>420.545685</y31>
			<x32>90.233686</x32>
			<y32>418.013661</y32>
			<x33>90.490979</x33>
			<y33>414.936537</y33>
			<x34>89.660024</x34>
			<y34>411.053933</y34>
			<x35>92.715167</x35>
			<y35>401.477015</y35>
			<x36>92.690612</x36>
			<y36>397.012814</y36>
			<x37>92.189904</x37>
			<y37>391.446248</y37>
			<x38>88.700246</x38>
			<y38>364.758366</y38>
			<x39>85.575355</x39>
			<y39>345.036294</y39>
			<x40>83.339784</x40>
			<y40>330.311358</y40>
			<x41>79.918453</x41>
			<y41>308.923576</y41>
			<x42>75.340547</x42>
			<y42>281.430213</y42>
			<x43>73.668672</x43>
			<y43>269.479433</y43>
			<x44>69.85019</x44>
			<y44>268.4744</y44>
			<x45>66.672985</x45>
			<y45>267.729752</y45>
			<x46>62.451303</x46>
			<y46>267.015518</y46>
			<x47>58.885489</x47>
			<y47>266.840299</y47>
			<x48>56.378743</x48>
			<y48>266.913297</y48>
			<x49>54.527865</x49>
			<y49>267.525311</y49>
			<x50>50.767745</x50>
			<y50>267.634808</y50>
			<x51>41.935771</x51>
			<y51>266.775772</y51>
			<x52>31.238328</x52>
			<y52>266.250117</y52>
			<x53>30.17926</x53>
			<y53>266.0019</y53>
		</polygon>
	</object>
	<object>
		<name>Metal</name>
		<pose>Unspecified</pose>
		<truncated>0</truncated>
		<difficult>0</difficult>
		<occluded>0</occluded>
		<bndbox>
			<xmin>48</xmin>
			<xmax>72</xmax>
			<ymin>417</ymin>
			<ymax>434</ymax>
		</bndbox>
		<polygon>
			<x1>47.396228</x1>
			<y1>430.981524</y1>
			<x2>47.663486</x2>
			<y2>432.089972</y2>
			<x3>48.751734</x3>
			<y3>432.895453</y3>
			<x4>50.243185</x4>
			<y4>433.410135</y4>
			<x5>51.705453</x5>
			<y5>433.367553</y5>
			<x6>53.959532</x6>
			<y6>432.464741</y6>
			<x7>56.407915</x7>
			<y7>431.277213</y7>
			<x8>58.229613</x8>
			<y8>430.107934</y8>
			<x9>66.71141</x9>
			<y9>424.279792</y9>
			<x10>68.338803</x10>
			<y10>423.39523</y10>
			<x11>69.713527</x11>
			<y11>421.680852</y11>
			<x12>70.446974</x12>
			<y12>419.706092</y12>
			<x13>70.539146</x13>
			<y13>417.470951</y13>
			<x14>69.6452</x14>
			<y14>416.380753</y14>
			<x15>67.123864</x15>
			<y15>416.175118</y15>
			<x16>64.257689</x16>
			<y16>417.374813</y16>
			<x17>61.794716</x17>
			<y17>418.283708</y17>
			<x18>58.569113</x18>
			<y18>420.610099</y18>
			<x19>54.731414</x19>
			<y19>423.233371</y19>
			<x20>49.698704</x20>
			<y20>427.007672</y20>
			<x21>48.459921</x21>
			<y21>427.322804</y21>
			<x22>47.488398</x22>
			<y22>428.746382</y22>
			<x23>46.934664</x23>
			<y23>430.157793</y23>
			<x24>47.396228</x24>
			<y24>430.981524</y24>
		</polygon>
	</object>
</annotation>